{
"meta":{"test_sets":[],"test_metrics":[],"learn_metrics":[{"best_value":"Min","name":"RMSE"}],"launch_mode":"Train","parameters":"","iteration_count":1000,"learn_sets":["learn"],"name":"experiment"},
"iterations":[
{"learn":[3731.064023],"iteration":0,"passed_time":0.1738974738,"remaining_time":173.7235763},
{"learn":[3493.179214],"iteration":1,"passed_time":0.1876508626,"remaining_time":93.63778042},
{"learn":[3270.757983],"iteration":2,"passed_time":0.1983905605,"remaining_time":65.93179626},
{"learn":[3073.224864],"iteration":3,"passed_time":0.2074455774,"remaining_time":51.65394877},
{"learn":[2881.455511],"iteration":4,"passed_time":0.2163298704,"remaining_time":43.04964421},
{"learn":[2710.099184],"iteration":5,"passed_time":0.2227209713,"remaining_time":36.89744091},
{"learn":[2550.151235],"iteration":6,"passed_time":0.2281435573,"remaining_time":32.3637932},
{"learn":[2406.739106],"iteration":7,"passed_time":0.2340563619,"remaining_time":29.02298888},
{"learn":[2271.406216],"iteration":8,"passed_time":0.2406865891,"remaining_time":26.50226776},
{"learn":[2147.644626],"iteration":9,"passed_time":0.2457886259,"remaining_time":24.33307397},
{"learn":[2034.548355],"iteration":10,"passed_time":0.2519953996,"remaining_time":22.65667729},
{"learn":[1931.400842],"iteration":11,"passed_time":0.2573904067,"remaining_time":21.19181015},
{"learn":[1831.14866],"iteration":12,"passed_time":0.2624670256,"remaining_time":19.92730417},
{"learn":[1742.307153],"iteration":13,"passed_time":0.267869246,"remaining_time":18.86564833},
{"learn":[1663.210322],"iteration":14,"passed_time":0.2745550365,"remaining_time":18.02911407},
{"learn":[1586.259746],"iteration":15,"passed_time":0.2795789304,"remaining_time":17.19410422},
{"learn":[1518.577448],"iteration":16,"passed_time":0.2854478395,"remaining_time":16.50560154},
{"learn":[1453.144883],"iteration":17,"passed_time":0.2903475026,"remaining_time":15.84006931},
{"learn":[1396.599353],"iteration":18,"passed_time":0.2953576756,"remaining_time":15.24978314},
{"learn":[1345.361153],"iteration":19,"passed_time":0.3014289301,"remaining_time":14.77001757},
{"learn":[1294.345399],"iteration":20,"passed_time":0.3061428616,"remaining_time":14.27208864},
{"learn":[1248.311025],"iteration":21,"passed_time":0.3109918678,"remaining_time":13.82500212},
{"learn":[1204.63114],"iteration":22,"passed_time":0.3166384452,"remaining_time":13.45025047},
{"learn":[1167.976623],"iteration":23,"passed_time":0.3220055561,"remaining_time":13.09489262},
{"learn":[1132.842628],"iteration":24,"passed_time":0.3277428566,"remaining_time":12.78197141},
{"learn":[1099.304612],"iteration":25,"passed_time":0.3337349589,"remaining_time":12.502225},
{"learn":[1070.452976],"iteration":26,"passed_time":0.3405378472,"remaining_time":12.27197501},
{"learn":[1040.798591],"iteration":27,"passed_time":0.3468641972,"remaining_time":12.04114285},
{"learn":[1015.142805],"iteration":28,"passed_time":0.3516933018,"remaining_time":11.77566193},
{"learn":[989.5887645],"iteration":29,"passed_time":0.3562042394,"remaining_time":11.51727041},
{"learn":[967.4143279],"iteration":30,"passed_time":0.3623806372,"remaining_time":11.32731734},
{"learn":[945.532451],"iteration":31,"passed_time":0.3672517682,"remaining_time":11.10936599},
{"learn":[928.8943223],"iteration":32,"passed_time":0.3722841828,"remaining_time":10.90905469},
{"learn":[910.4760858],"iteration":33,"passed_time":0.3784482859,"remaining_time":10.75238365},
{"learn":[890.8815917],"iteration":34,"passed_time":0.383471034,"remaining_time":10.57284422},
{"learn":[873.9323598],"iteration":35,"passed_time":0.3884792786,"remaining_time":10.40261179},
{"learn":[859.3556573],"iteration":36,"passed_time":0.3970519321,"remaining_time":10.33408137},
{"learn":[844.700532],"iteration":37,"passed_time":0.4044674873,"remaining_time":10.23941376},
{"learn":[830.3099952],"iteration":38,"passed_time":0.4102540375,"remaining_time":10.10908026},
{"learn":[819.3217664],"iteration":39,"passed_time":0.4153082016,"remaining_time":9.967396838},
{"learn":[805.9548426],"iteration":40,"passed_time":0.4206702329,"remaining_time":9.839579351},
{"learn":[796.2289578],"iteration":41,"passed_time":0.4259829808,"remaining_time":9.716468942},
{"learn":[785.6160951],"iteration":42,"passed_time":0.4305576839,"remaining_time":9.58241171},
{"learn":[778.065445],"iteration":43,"passed_time":0.4355185845,"remaining_time":9.462631064},
{"learn":[768.2114271],"iteration":44,"passed_time":0.4415678429,"remaining_time":9.371050887},
{"learn":[760.9319658],"iteration":45,"passed_time":0.4460919362,"remaining_time":9.25155885},
{"learn":[754.050786],"iteration":46,"passed_time":0.4505684282,"remaining_time":9.135993874},
{"learn":[747.1857813],"iteration":47,"passed_time":0.4558430563,"remaining_time":9.040887284},
{"learn":[740.4694079],"iteration":48,"passed_time":0.4618310457,"remaining_time":8.963292337},
{"learn":[735.3443732],"iteration":49,"passed_time":0.4661826888,"remaining_time":8.857471086},
{"learn":[729.1606826],"iteration":50,"passed_time":0.4713317846,"remaining_time":8.770467913},
{"learn":[723.7526834],"iteration":51,"passed_time":0.4771571951,"remaining_time":8.69894271},
{"learn":[718.0762824],"iteration":52,"passed_time":0.4811396475,"remaining_time":8.596966909},
{"learn":[713.1820511],"iteration":53,"passed_time":0.4858147067,"remaining_time":8.510753937},
{"learn":[709.4803494],"iteration":54,"passed_time":0.4914004255,"remaining_time":8.443152766},
{"learn":[705.796549],"iteration":55,"passed_time":0.4965301501,"remaining_time":8.370079674},
{"learn":[700.7654106],"iteration":56,"passed_time":0.5011870878,"remaining_time":8.291568838},
{"learn":[697.4780987],"iteration":57,"passed_time":0.5069227485,"remaining_time":8.233124639},
{"learn":[693.6624452],"iteration":58,"passed_time":0.5138542737,"remaining_time":8.195540196},
{"learn":[688.1713378],"iteration":59,"passed_time":0.5211429319,"remaining_time":8.1645726},
{"learn":[685.4884092],"iteration":60,"passed_time":0.5264068771,"remaining_time":8.103214059},
{"learn":[682.4524549],"iteration":61,"passed_time":0.5323715073,"remaining_time":8.054265707},
{"learn":[678.2941299],"iteration":62,"passed_time":0.5379495375,"remaining_time":8.000932011},
{"learn":[674.359778],"iteration":63,"passed_time":0.5433908369,"remaining_time":7.94709099},
{"learn":[670.5563991],"iteration":64,"passed_time":0.5491472776,"remaining_time":7.899272378},
{"learn":[668.1299258],"iteration":65,"passed_time":0.5558323971,"remaining_time":7.865870589},
{"learn":[665.5544838],"iteration":66,"passed_time":0.5606016532,"remaining_time":7.8065872},
{"learn":[663.4836071],"iteration":67,"passed_time":0.5656486789,"remaining_time":7.752714246},
{"learn":[661.3683593],"iteration":68,"passed_time":0.5728209207,"remaining_time":7.728931553},
{"learn":[658.7616842],"iteration":69,"passed_time":0.578004547,"remaining_time":7.679203267},
{"learn":[656.8595217],"iteration":70,"passed_time":0.5849529801,"remaining_time":7.653821387},
{"learn":[654.2297823],"iteration":71,"passed_time":0.5908866232,"remaining_time":7.615872033},
{"learn":[651.6397711],"iteration":72,"passed_time":0.5957463788,"remaining_time":7.56516292},
{"learn":[648.7330952],"iteration":73,"passed_time":0.600797447,"remaining_time":7.518086972},
{"learn":[646.4655226],"iteration":74,"passed_time":0.6075510662,"remaining_time":7.493129816},
{"learn":[644.4970038],"iteration":75,"passed_time":0.6131304565,"remaining_time":7.45437555},
{"learn":[642.32651],"iteration":76,"passed_time":0.6197562916,"remaining_time":7.429026716},
{"learn":[641.050161],"iteration":77,"passed_time":0.6251440502,"remaining_time":7.38952326},
{"learn":[639.8194735],"iteration":78,"passed_time":0.6296221988,"remaining_time":7.340279052},
{"learn":[636.9902576],"iteration":79,"passed_time":0.6362627754,"remaining_time":7.317021918},
{"learn":[634.1688319],"iteration":80,"passed_time":0.6423158543,"remaining_time":7.287509507},
{"learn":[631.6767379],"iteration":81,"passed_time":0.6465495916,"remaining_time":7.238201526},
{"learn":[630.878739],"iteration":82,"passed_time":0.6537683113,"remaining_time":7.222958331},
{"learn":[629.1950611],"iteration":83,"passed_time":0.6591536643,"remaining_time":7.187913768},
{"learn":[627.922514],"iteration":84,"passed_time":0.6635257149,"remaining_time":7.142659167},
{"learn":[626.7985135],"iteration":85,"passed_time":0.6717014764,"remaining_time":7.138780807},
{"learn":[625.6008282],"iteration":86,"passed_time":0.6765841556,"remaining_time":7.10024522},
{"learn":[624.3940968],"iteration":87,"passed_time":0.6825079831,"remaining_time":7.073264552},
{"learn":[623.4251272],"iteration":88,"passed_time":0.6898589726,"remaining_time":7.061365439},
{"learn":[622.4780729],"iteration":89,"passed_time":0.694090711,"remaining_time":7.0180283},
{"learn":[621.3960716],"iteration":90,"passed_time":0.7016232506,"remaining_time":7.00852236},
{"learn":[618.9961658],"iteration":91,"passed_time":0.7086706669,"remaining_time":6.994271365},
{"learn":[616.568379],"iteration":92,"passed_time":0.7178329548,"remaining_time":7.000800968},
{"learn":[615.5592753],"iteration":93,"passed_time":0.7233312724,"remaining_time":6.971682264},
{"learn":[614.5379268],"iteration":94,"passed_time":0.7294060192,"remaining_time":6.948552077},
{"learn":[613.8100374],"iteration":95,"passed_time":0.7364405044,"remaining_time":6.93481475},
{"learn":[612.6041843],"iteration":96,"passed_time":0.7416752932,"remaining_time":6.90446175},
{"learn":[611.565372],"iteration":97,"passed_time":0.7510156088,"remaining_time":6.91240897},
{"learn":[609.9356263],"iteration":98,"passed_time":0.7558297294,"remaining_time":6.878814002},
{"learn":[608.6542762],"iteration":99,"passed_time":0.7602129847,"remaining_time":6.841916862},
{"learn":[605.693558],"iteration":100,"passed_time":0.7668707211,"remaining_time":6.825908696},
{"learn":[605.008775],"iteration":101,"passed_time":0.7713543305,"remaining_time":6.790943027},
{"learn":[603.4703146],"iteration":102,"passed_time":0.776876171,"remaining_time":6.765610926},
{"learn":[602.8302884],"iteration":103,"passed_time":0.7823415179,"remaining_time":6.740173077},
{"learn":[602.0984499],"iteration":104,"passed_time":0.7868038606,"remaining_time":6.70656624},
{"learn":[599.7309951],"iteration":105,"passed_time":0.7912310761,"remaining_time":6.673213038},
{"learn":[598.9884007],"iteration":106,"passed_time":0.7982537153,"remaining_time":6.662061381},
{"learn":[598.1246952],"iteration":107,"passed_time":0.8029455913,"remaining_time":6.63173581},
{"learn":[595.7435277],"iteration":108,"passed_time":0.8080268123,"remaining_time":6.605063209},
{"learn":[594.466191],"iteration":109,"passed_time":0.8142579993,"remaining_time":6.588087449},
{"learn":[593.6077063],"iteration":110,"passed_time":0.8195587489,"remaining_time":6.563853403},
{"learn":[592.6626077],"iteration":111,"passed_time":0.8249843129,"remaining_time":6.540947052},
{"learn":[591.6296145],"iteration":112,"passed_time":0.833296274,"remaining_time":6.541007036},
{"learn":[590.7680621],"iteration":113,"passed_time":0.8374791182,"remaining_time":6.508828936},
{"learn":[589.3776223],"iteration":114,"passed_time":0.8440288797,"remaining_time":6.495352683},
{"learn":[587.4597752],"iteration":115,"passed_time":0.8501818243,"remaining_time":6.478971834},
{"learn":[586.2081661],"iteration":116,"passed_time":0.8543935865,"remaining_time":6.4481157},
{"learn":[585.6858901],"iteration":117,"passed_time":0.8598623304,"remaining_time":6.427106572},
{"learn":[584.1396047],"iteration":118,"passed_time":0.8656500716,"remaining_time":6.408720278},
{"learn":[583.1236603],"iteration":119,"passed_time":0.8701834309,"remaining_time":6.38134516},
{"learn":[582.3569931],"iteration":120,"passed_time":0.8757063503,"remaining_time":6.361536214},
{"learn":[581.7414866],"iteration":121,"passed_time":0.8812090819,"remaining_time":6.34181618},
{"learn":[580.8265266],"iteration":122,"passed_time":0.8857955511,"remaining_time":6.315794295},
{"learn":[580.1919223],"iteration":123,"passed_time":0.8906285723,"remaining_time":6.291859914},
{"learn":[579.500832],"iteration":124,"passed_time":0.8958941498,"remaining_time":6.271259049},
{"learn":[579.0607566],"iteration":125,"passed_time":0.9007844153,"remaining_time":6.248298246},
{"learn":[578.2227354],"iteration":126,"passed_time":0.9062881804,"remaining_time":6.229839225},
{"learn":[577.8846722],"iteration":127,"passed_time":0.9122235738,"remaining_time":6.214523097},
{"learn":[576.6209643],"iteration":128,"passed_time":0.9169147112,"remaining_time":6.190951267},
{"learn":[576.2217503],"iteration":129,"passed_time":0.922253272,"remaining_time":6.172002667},
{"learn":[574.6496932],"iteration":130,"passed_time":0.9284361475,"remaining_time":6.158862689},
{"learn":[574.255779],"iteration":131,"passed_time":0.9328781029,"remaining_time":6.134380252},
{"learn":[572.8984386],"iteration":132,"passed_time":0.9390122503,"remaining_time":6.121230233},
{"learn":[572.1753622],"iteration":133,"passed_time":0.9438607447,"remaining_time":6.099876156},
{"learn":[571.4537029],"iteration":134,"passed_time":0.9479567231,"remaining_time":6.073944929},
{"learn":[570.6722304],"iteration":135,"passed_time":0.9521033302,"remaining_time":6.048656451},
{"learn":[570.4197743],"iteration":136,"passed_time":0.9587005925,"remaining_time":6.039113951},
{"learn":[568.936082],"iteration":137,"passed_time":0.9633375572,"remaining_time":6.017369379},
{"learn":[567.6717585],"iteration":138,"passed_time":0.9677325257,"remaining_time":5.994371976},
{"learn":[566.7979379],"iteration":139,"passed_time":0.9745577554,"remaining_time":5.986569069},
{"learn":[565.9410422],"iteration":140,"passed_time":0.9790342857,"remaining_time":5.964471287},
{"learn":[565.3209902],"iteration":141,"passed_time":0.9829827141,"remaining_time":5.939430766},
{"learn":[564.7319576],"iteration":142,"passed_time":0.9886274769,"remaining_time":5.924851382},
{"learn":[564.1878864],"iteration":143,"passed_time":0.9933175568,"remaining_time":5.904721032},
{"learn":[563.9083656],"iteration":144,"passed_time":0.9974779149,"remaining_time":5.881680119},
{"learn":[563.1998049],"iteration":145,"passed_time":1.003164908,"remaining_time":5.867827611},
{"learn":[562.1908004],"iteration":146,"passed_time":1.007938887,"remaining_time":5.848788236},
{"learn":[561.8007322],"iteration":147,"passed_time":1.013960248,"remaining_time":5.837122507},
{"learn":[561.4500503],"iteration":148,"passed_time":1.018818336,"remaining_time":5.818888617},
{"learn":[561.0954295],"iteration":149,"passed_time":1.024275717,"remaining_time":5.804229064},
{"learn":[560.7468805],"iteration":150,"passed_time":1.029347928,"remaining_time":5.787525766},
{"learn":[559.8946183],"iteration":151,"passed_time":1.034519294,"remaining_time":5.771528691},
{"learn":[559.5724178],"iteration":152,"passed_time":1.039553137,"remaining_time":5.754911812},
{"learn":[558.9714746],"iteration":153,"passed_time":1.044483092,"remaining_time":5.737874648},
{"learn":[558.4097937],"iteration":154,"passed_time":1.048533503,"remaining_time":5.716198772},
{"learn":[557.9080497],"iteration":155,"passed_time":1.053834023,"remaining_time":5.701512278},
{"learn":[557.2445457],"iteration":156,"passed_time":1.058804692,"remaining_time":5.685174239},
{"learn":[556.7566593],"iteration":157,"passed_time":1.063234775,"remaining_time":5.666099243},
{"learn":[556.3445944],"iteration":158,"passed_time":1.067904818,"remaining_time":5.648477685},
{"learn":[555.8599296],"iteration":159,"passed_time":1.073428494,"remaining_time":5.635499592},
{"learn":[554.9908983],"iteration":160,"passed_time":1.083279113,"remaining_time":5.645162582},
{"learn":[554.4804149],"iteration":161,"passed_time":1.092229237,"remaining_time":5.649926544},
{"learn":[554.2158955],"iteration":162,"passed_time":1.101967913,"remaining_time":5.658571431},
{"learn":[553.7662659],"iteration":163,"passed_time":1.111792408,"remaining_time":5.667429594},
{"learn":[553.3144562],"iteration":164,"passed_time":1.121612835,"remaining_time":5.676040712},
{"learn":[552.8953268],"iteration":165,"passed_time":1.1297745,"remaining_time":5.676095981},
{"learn":[552.1471809],"iteration":166,"passed_time":1.138831838,"remaining_time":5.680520486},
{"learn":[551.9137133],"iteration":167,"passed_time":1.145671206,"remaining_time":5.673800256},
{"learn":[551.5919315],"iteration":168,"passed_time":1.156109227,"remaining_time":5.684773773},
{"learn":[551.2998436],"iteration":169,"passed_time":1.161002809,"remaining_time":5.668425477},
{"learn":[550.8189486],"iteration":170,"passed_time":1.169031575,"remaining_time":5.667410383},
{"learn":[550.4913129],"iteration":171,"passed_time":1.174537921,"remaining_time":5.654170923},
{"learn":[549.8319685],"iteration":172,"passed_time":1.180725657,"remaining_time":5.64427814},
{"learn":[549.4057434],"iteration":173,"passed_time":1.185954809,"remaining_time":5.629877428},
{"learn":[549.0116426],"iteration":174,"passed_time":1.191876525,"remaining_time":5.618846476},
{"learn":[548.7079967],"iteration":175,"passed_time":1.197674676,"remaining_time":5.607295072},
{"learn":[548.3675242],"iteration":176,"passed_time":1.202735903,"remaining_time":5.592382191},
{"learn":[547.7741986],"iteration":177,"passed_time":1.207881142,"remaining_time":5.577967968},
{"learn":[547.4458911],"iteration":178,"passed_time":1.214348147,"remaining_time":5.569719713},
{"learn":[547.2578402],"iteration":179,"passed_time":1.220371601,"remaining_time":5.559470628},
{"learn":[547.1109833],"iteration":180,"passed_time":1.22442114,"remaining_time":5.540336542},
{"learn":[546.9941717],"iteration":181,"passed_time":1.230932888,"remaining_time":5.532434626},
{"learn":[546.621514],"iteration":182,"passed_time":1.238796658,"remaining_time":5.530583985},
{"learn":[546.4077673],"iteration":183,"passed_time":1.244284176,"remaining_time":5.518129824},
{"learn":[546.0879008],"iteration":184,"passed_time":1.252561445,"remaining_time":5.518040958},
{"learn":[545.7211483],"iteration":185,"passed_time":1.257171677,"remaining_time":5.501815832},
{"learn":[545.3130903],"iteration":186,"passed_time":1.26302022,"remaining_time":5.491098605},
{"learn":[545.0352351],"iteration":187,"passed_time":1.268788643,"remaining_time":5.480087118},
{"learn":[544.7027058],"iteration":188,"passed_time":1.273377929,"remaining_time":5.464071432},
{"learn":[544.2912696],"iteration":189,"passed_time":1.278968433,"remaining_time":5.452444372},
{"learn":[544.1444031],"iteration":190,"passed_time":1.284698549,"remaining_time":5.441471863},
{"learn":[543.7897722],"iteration":191,"passed_time":1.288863643,"remaining_time":5.423967832},
{"learn":[543.5487546],"iteration":192,"passed_time":1.29472871,"remaining_time":5.413710202},
{"learn":[543.3459987],"iteration":193,"passed_time":1.301482798,"remaining_time":5.407191417},
{"learn":[542.9465289],"iteration":194,"passed_time":1.307039563,"remaining_time":5.395727429},
{"learn":[542.0470212],"iteration":195,"passed_time":1.313218901,"remaining_time":5.386877532},
{"learn":[541.7536061],"iteration":196,"passed_time":1.318234177,"remaining_time":5.373309869},
{"learn":[541.2833623],"iteration":197,"passed_time":1.323053277,"remaining_time":5.359033982},
{"learn":[540.6912379],"iteration":198,"passed_time":1.3289444,"remaining_time":5.349168162},
{"learn":[540.5001679],"iteration":199,"passed_time":1.334243692,"remaining_time":5.336974769},
{"learn":[540.1966524],"iteration":200,"passed_time":1.339476441,"remaining_time":5.324585454},
{"learn":[539.874719],"iteration":201,"passed_time":1.345772775,"remaining_time":5.316468686},
{"learn":[539.5890066],"iteration":202,"passed_time":1.351442561,"remaining_time":5.305909955},
{"learn":[538.8032736],"iteration":203,"passed_time":1.356489808,"remaining_time":5.292970033},
{"learn":[538.5908169],"iteration":204,"passed_time":1.36258333,"remaining_time":5.284164623},
{"learn":[538.332391],"iteration":205,"passed_time":1.367221541,"remaining_time":5.269776232},
{"learn":[538.1398335],"iteration":206,"passed_time":1.37214773,"remaining_time":5.256585266},
{"learn":[537.7370506],"iteration":207,"passed_time":1.378497214,"remaining_time":5.248893238},
{"learn":[537.3099009],"iteration":208,"passed_time":1.383593789,"remaining_time":5.236472186},
{"learn":[536.9426797],"iteration":209,"passed_time":1.38884184,"remaining_time":5.224690731},
{"learn":[536.2534662],"iteration":210,"passed_time":1.394677821,"remaining_time":5.215169673},
{"learn":[536.1503467],"iteration":211,"passed_time":1.399703215,"remaining_time":5.202670442},
{"learn":[535.7683004],"iteration":212,"passed_time":1.40498984,"remaining_time":5.191206591},
{"learn":[535.7048677],"iteration":213,"passed_time":1.411038352,"remaining_time":5.182598807},
{"learn":[535.4328523],"iteration":214,"passed_time":1.415839579,"remaining_time":5.169460789},
{"learn":[534.8573305],"iteration":215,"passed_time":1.421100834,"remaining_time":5.158069694},
{"learn":[534.33628],"iteration":216,"passed_time":1.427505756,"remaining_time":5.150861785},
{"learn":[533.7255469],"iteration":217,"passed_time":1.432606531,"remaining_time":5.13898306},
{"learn":[533.3987168],"iteration":218,"passed_time":1.438495686,"remaining_time":5.129977768},
{"learn":[532.9236182],"iteration":219,"passed_time":1.444270144,"remaining_time":5.120594145},
{"learn":[532.6627818],"iteration":220,"passed_time":1.449040703,"remaining_time":5.107704559},
{"learn":[532.5214301],"iteration":221,"passed_time":1.453438959,"remaining_time":5.093583377},
{"learn":[532.4041603],"iteration":222,"passed_time":1.459428495,"remaining_time":5.085093905},
{"learn":[532.2098377],"iteration":223,"passed_time":1.464283305,"remaining_time":5.072695736},
{"learn":[531.9758468],"iteration":224,"passed_time":1.46877719,"remaining_time":5.059121431},
{"learn":[531.2990807],"iteration":225,"passed_time":1.474865759,"remaining_time":5.051088926},
{"learn":[531.0569353],"iteration":226,"passed_time":1.480031716,"remaining_time":5.039931792},
{"learn":[530.8339839],"iteration":227,"passed_time":1.485109722,"remaining_time":5.028529409},
{"learn":[530.5287965],"iteration":228,"passed_time":1.491887881,"remaining_time":5.022906358},
{"learn":[530.2506972],"iteration":229,"passed_time":1.496790982,"remaining_time":5.010995895},
{"learn":[530.1833996],"iteration":230,"passed_time":1.501258344,"remaining_time":4.997695525},
{"learn":[529.9265053],"iteration":231,"passed_time":1.507098546,"remaining_time":4.989015877},
{"learn":[529.5078666],"iteration":232,"passed_time":1.512149508,"remaining_time":4.977762543},
{"learn":[529.1614624],"iteration":233,"passed_time":1.517457949,"remaining_time":4.967405081},
{"learn":[528.897118],"iteration":234,"passed_time":1.524456492,"remaining_time":4.96259241},
{"learn":[528.341049],"iteration":235,"passed_time":1.53078592,"remaining_time":4.955595098},
{"learn":[528.3309374],"iteration":236,"passed_time":1.536340199,"remaining_time":4.946107898},
{"learn":[528.1072273],"iteration":237,"passed_time":1.541797727,"remaining_time":4.936343984},
{"learn":[527.9220921],"iteration":238,"passed_time":1.546916508,"remaining_time":4.925537501},
{"learn":[527.8478273],"iteration":239,"passed_time":1.55197168,"remaining_time":4.914576986},
{"learn":[527.7685279],"iteration":240,"passed_time":1.557141266,"remaining_time":4.904025813},
{"learn":[527.2247962],"iteration":241,"passed_time":1.562391464,"remaining_time":4.893771609},
{"learn":[526.9016998],"iteration":242,"passed_time":1.566736832,"remaining_time":4.880739842},
{"learn":[526.7128004],"iteration":243,"passed_time":1.572143952,"remaining_time":4.871068965},
{"learn":[526.5180355],"iteration":244,"passed_time":1.577363741,"remaining_time":4.860855611},
{"learn":[526.2902225],"iteration":245,"passed_time":1.582250526,"remaining_time":4.84966218},
{"learn":[526.1600089],"iteration":246,"passed_time":1.588931128,"remaining_time":4.84398842},
{"learn":[525.7831908],"iteration":247,"passed_time":1.59411461,"remaining_time":4.833766882},
{"learn":[525.4843958],"iteration":248,"passed_time":1.599353941,"remaining_time":4.823754254},
{"learn":[524.9944123],"iteration":249,"passed_time":1.605404007,"remaining_time":4.81621202},
{"learn":[524.7361612],"iteration":250,"passed_time":1.610484737,"remaining_time":4.805789117},
{"learn":[524.5370286],"iteration":251,"passed_time":1.616632446,"remaining_time":4.798575674},
{"learn":[524.1024579],"iteration":252,"passed_time":1.622536176,"remaining_time":4.790650289},
{"learn":[523.943192],"iteration":253,"passed_time":1.629487315,"remaining_time":4.785817075},
{"learn":[523.5524835],"iteration":254,"passed_time":1.635926725,"remaining_time":4.779472196},
{"learn":[523.4810052],"iteration":255,"passed_time":1.641833486,"remaining_time":4.77157857},
{"learn":[523.4412771],"iteration":256,"passed_time":1.646105175,"remaining_time":4.758973326},
{"learn":[522.9731887],"iteration":257,"passed_time":1.652650454,"remaining_time":4.752971462},
{"learn":[522.7339176],"iteration":258,"passed_time":1.657967644,"remaining_time":4.743451831},
{"learn":[522.6695863],"iteration":259,"passed_time":1.662022701,"remaining_time":4.730372304},
{"learn":[522.2927757],"iteration":260,"passed_time":1.66864218,"remaining_time":4.724622878},
{"learn":[522.1111589],"iteration":261,"passed_time":1.673390956,"remaining_time":4.713597427},
{"learn":[521.7075325],"iteration":262,"passed_time":1.678325512,"remaining_time":4.703140314},
{"learn":[521.2491858],"iteration":263,"passed_time":1.68595322,"remaining_time":4.700233218},
{"learn":[521.0653802],"iteration":264,"passed_time":1.690934786,"remaining_time":4.689951199},
{"learn":[520.8745162],"iteration":265,"passed_time":1.695583998,"remaining_time":4.678791935},
{"learn":[520.5653902],"iteration":266,"passed_time":1.70138285,"remaining_time":4.670837561},
{"learn":[520.2500006],"iteration":267,"passed_time":1.706612753,"remaining_time":4.66134528},
{"learn":[519.957107],"iteration":268,"passed_time":1.711265273,"remaining_time":4.650315667},
{"learn":[519.5466521],"iteration":269,"passed_time":1.717540619,"remaining_time":4.643720934},
{"learn":[519.3120459],"iteration":270,"passed_time":1.722626584,"remaining_time":4.633929077},
{"learn":[519.0952177],"iteration":271,"passed_time":1.728314242,"remaining_time":4.625782236},
{"learn":[518.8931148],"iteration":272,"passed_time":1.733607195,"remaining_time":4.616602311},
{"learn":[518.5654381],"iteration":273,"passed_time":1.739326015,"remaining_time":4.608579149},
{"learn":[518.5064029],"iteration":274,"passed_time":1.746184649,"remaining_time":4.60357771},
{"learn":[518.2492434],"iteration":275,"passed_time":1.752808192,"remaining_time":4.597946128},
{"learn":[517.9485228],"iteration":276,"passed_time":1.757371654,"remaining_time":4.586930345},
{"learn":[517.943286],"iteration":277,"passed_time":1.761723437,"remaining_time":4.575411228},
{"learn":[517.6549979],"iteration":278,"passed_time":1.768211037,"remaining_time":4.569462932},
{"learn":[517.5365688],"iteration":279,"passed_time":1.77226008,"remaining_time":4.557240206},
{"learn":[517.2788866],"iteration":280,"passed_time":1.77884632,"remaining_time":4.55156763},
{"learn":[517.1034225],"iteration":281,"passed_time":1.78561475,"remaining_time":4.546352449},
{"learn":[516.9539596],"iteration":282,"passed_time":1.790954897,"remaining_time":4.537507637},
{"learn":[516.6572823],"iteration":283,"passed_time":1.79749396,"remaining_time":4.531710124},
{"learn":[516.6235495],"iteration":284,"passed_time":1.802542647,"remaining_time":4.522168396},
{"learn":[516.446207],"iteration":285,"passed_time":1.806927277,"remaining_time":4.511000266},
{"learn":[516.1327686],"iteration":286,"passed_time":1.813357813,"remaining_time":4.504962092},
{"learn":[516.0255892],"iteration":287,"passed_time":1.818842482,"remaining_time":4.496582802},
{"learn":[515.8397526],"iteration":288,"passed_time":1.823027778,"remaining_time":4.485026816},
{"learn":[515.4717501],"iteration":289,"passed_time":1.829333226,"remaining_time":4.478712382},
{"learn":[515.2985626],"iteration":290,"passed_time":1.835557196,"remaining_time":4.472199492},
{"learn":[515.1893694],"iteration":291,"passed_time":1.840040931,"remaining_time":4.461469107},
{"learn":[515.0626196],"iteration":292,"passed_time":1.847009538,"remaining_time":4.456777281},
{"learn":[514.7156081],"iteration":293,"passed_time":1.851864885,"remaining_time":4.446995268},
{"learn":[514.5466822],"iteration":294,"passed_time":1.857320668,"remaining_time":4.438681595},
{"learn":[514.2770303],"iteration":295,"passed_time":1.862876361,"remaining_time":4.430624859},
{"learn":[513.9715694],"iteration":296,"passed_time":1.86767978,"remaining_time":4.420804327},
{"learn":[513.7168207],"iteration":297,"passed_time":1.874506999,"remaining_time":4.415784943},
{"learn":[513.4797717],"iteration":298,"passed_time":1.881502955,"remaining_time":4.411149068},
{"learn":[513.3432129],"iteration":299,"passed_time":1.887504151,"remaining_time":4.404176352},
{"learn":[513.2414268],"iteration":300,"passed_time":1.894858541,"remaining_time":4.400352559},
{"learn":[512.8955991],"iteration":301,"passed_time":1.899228732,"remaining_time":4.389608128},
{"learn":[512.8778981],"iteration":302,"passed_time":1.903175652,"remaining_time":4.377932111},
{"learn":[512.6010551],"iteration":303,"passed_time":1.909012602,"remaining_time":4.370634116},
{"learn":[512.38117],"iteration":304,"passed_time":1.913654034,"remaining_time":4.360621487},
{"learn":[512.1541988],"iteration":305,"passed_time":1.917765993,"remaining_time":4.349443135},
{"learn":[511.8664542],"iteration":306,"passed_time":1.923205464,"remaining_time":4.341307447},
{"learn":[511.7652047],"iteration":307,"passed_time":1.92853999,"remaining_time":4.332953485},
{"learn":[511.6123306],"iteration":308,"passed_time":1.933090216,"remaining_time":4.322865175},
{"learn":[511.308527],"iteration":309,"passed_time":1.938251984,"remaining_time":4.31417377},
{"learn":[511.1091624],"iteration":310,"passed_time":1.943445566,"remaining_time":4.305575546},
{"learn":[510.8843542],"iteration":311,"passed_time":1.94838938,"remaining_time":4.296448376},
{"learn":[510.7037587],"iteration":312,"passed_time":1.955072032,"remaining_time":4.291164491},
{"learn":[510.372867],"iteration":313,"passed_time":1.960868843,"remaining_time":4.28393639},
{"learn":[510.145136],"iteration":314,"passed_time":1.965376633,"remaining_time":4.273914266},
{"learn":[509.9103833],"iteration":315,"passed_time":1.970846674,"remaining_time":4.266009889},
{"learn":[509.8055537],"iteration":316,"passed_time":1.977083398,"remaining_time":4.259772747},
{"learn":[509.4899691],"iteration":317,"passed_time":1.981777494,"remaining_time":4.250227203},
{"learn":[509.2182589],"iteration":318,"passed_time":1.986322311,"remaining_time":4.240393397},
{"learn":[509.2138089],"iteration":319,"passed_time":1.992240891,"remaining_time":4.233511893},
{"learn":[509.0596168],"iteration":320,"passed_time":1.996947576,"remaining_time":4.22407291},
{"learn":[509.0554964],"iteration":321,"passed_time":2.001456838,"remaining_time":4.214247627},
{"learn":[508.9772849],"iteration":322,"passed_time":2.007786427,"remaining_time":4.208270622},
{"learn":[508.6931608],"iteration":323,"passed_time":2.013107655,"remaining_time":4.200187577},
{"learn":[508.3779748],"iteration":324,"passed_time":2.02017899,"remaining_time":4.195756363},
{"learn":[508.1575929],"iteration":325,"passed_time":2.025840734,"remaining_time":4.188394646},
{"learn":[508.0132692],"iteration":326,"passed_time":2.030382983,"remaining_time":4.17873929},
{"learn":[507.9589654],"iteration":327,"passed_time":2.035522518,"remaining_time":4.170338818},
{"learn":[507.6932021],"iteration":328,"passed_time":2.041366236,"remaining_time":4.16339436},
{"learn":[507.4266423],"iteration":329,"passed_time":2.046598111,"remaining_time":4.155214347},
{"learn":[507.2584211],"iteration":330,"passed_time":2.05239644,"remaining_time":4.148197034},
{"learn":[506.9279356],"iteration":331,"passed_time":2.057935355,"remaining_time":4.140665112},
{"learn":[506.7774789],"iteration":332,"passed_time":2.061738534,"remaining_time":4.129668475},
{"learn":[506.5812816],"iteration":333,"passed_time":2.066162752,"remaining_time":4.119953271},
{"learn":[506.5119412],"iteration":334,"passed_time":2.072467483,"remaining_time":4.114002615},
{"learn":[506.2578801],"iteration":335,"passed_time":2.077864054,"remaining_time":4.106255155},
{"learn":[506.0341107],"iteration":336,"passed_time":2.082054086,"remaining_time":4.09614795},
{"learn":[505.8689429],"iteration":337,"passed_time":2.088185336,"remaining_time":4.089877789},
{"learn":[505.7203813],"iteration":338,"passed_time":2.092244344,"remaining_time":4.079567881},
{"learn":[505.6623724],"iteration":339,"passed_time":2.096252291,"remaining_time":4.069195623},
{"learn":[505.659387],"iteration":340,"passed_time":2.101208635,"remaining_time":4.06069352},
{"learn":[505.4012698],"iteration":341,"passed_time":2.105954432,"remaining_time":4.051807064},
{"learn":[505.0869395],"iteration":342,"passed_time":2.11041803,"remaining_time":4.042404215},
{"learn":[504.7487861],"iteration":343,"passed_time":2.115383259,"remaining_time":4.03398668},
{"learn":[504.5538341],"iteration":344,"passed_time":2.122619125,"remaining_time":4.029900077},
{"learn":[504.3017481],"iteration":345,"passed_time":2.126666568,"remaining_time":4.0197686},
{"learn":[504.176879],"iteration":346,"passed_time":2.131455721,"remaining_time":4.01106797},
{"learn":[504.0296786],"iteration":347,"passed_time":2.137157723,"remaining_time":4.004100101},
{"learn":[503.839266],"iteration":348,"passed_time":2.141330878,"remaining_time":3.994287684},
{"learn":[503.552496],"iteration":349,"passed_time":2.145571329,"remaining_time":3.984632469},
{"learn":[503.549639],"iteration":350,"passed_time":2.150829727,"remaining_time":3.976890293},
{"learn":[503.2987534],"iteration":351,"passed_time":2.156403063,"remaining_time":3.969742002},
{"learn":[502.9987131],"iteration":352,"passed_time":2.161057006,"remaining_time":3.960917515},
{"learn":[502.9516573],"iteration":353,"passed_time":2.16731221,"remaining_time":3.955038665},
{"learn":[502.6902255],"iteration":354,"passed_time":2.172057474,"remaining_time":3.946414284},
{"learn":[502.5576156],"iteration":355,"passed_time":2.175938889,"remaining_time":3.936249002},
{"learn":[502.4976256],"iteration":356,"passed_time":2.182207823,"remaining_time":3.930419133},
{"learn":[502.3077266],"iteration":357,"passed_time":2.18775239,"remaining_time":3.923287805},
{"learn":[502.0663321],"iteration":358,"passed_time":2.192214331,"remaining_time":3.914232274},
{"learn":[501.8406489],"iteration":359,"passed_time":2.197100323,"remaining_time":3.905956131},
{"learn":[501.7974809],"iteration":360,"passed_time":2.201999414,"remaining_time":3.897721955},
{"learn":[501.5846096],"iteration":361,"passed_time":2.206921275,"remaining_time":3.889546335},
{"learn":[501.3378784],"iteration":362,"passed_time":2.212040871,"remaining_time":3.881735634},
{"learn":[501.1977347],"iteration":363,"passed_time":2.217556478,"remaining_time":3.874631648},
{"learn":[501.0035141],"iteration":364,"passed_time":2.222117337,"remaining_time":3.865875367},
{"learn":[500.6091145],"iteration":365,"passed_time":2.226480453,"remaining_time":3.856799473},
{"learn":[500.4022578],"iteration":366,"passed_time":2.232629117,"remaining_time":3.850828967},
{"learn":[500.1125949],"iteration":367,"passed_time":2.23784942,"remaining_time":3.843263135},
{"learn":[499.959252],"iteration":368,"passed_time":2.242974818,"remaining_time":3.835547723},
{"learn":[499.8062965],"iteration":369,"passed_time":2.24854607,"remaining_time":3.82860547},
{"learn":[499.7651866],"iteration":370,"passed_time":2.253447201,"remaining_time":3.820534474},
{"learn":[499.7141185],"iteration":371,"passed_time":2.259680956,"remaining_time":3.814730216},
{"learn":[499.4434225],"iteration":372,"passed_time":2.264870816,"remaining_time":3.807168906},
{"learn":[499.3382407],"iteration":373,"passed_time":2.270028474,"remaining_time":3.799566376},
{"learn":[499.1373411],"iteration":374,"passed_time":2.27523473,"remaining_time":3.792057883},
{"learn":[498.9322839],"iteration":375,"passed_time":2.281292265,"remaining_time":3.785974397},
{"learn":[498.7871486],"iteration":376,"passed_time":2.285316345,"remaining_time":3.776530724},
{"learn":[498.598679],"iteration":377,"passed_time":2.289909474,"remaining_time":3.768052098},
{"learn":[498.5607722],"iteration":378,"passed_time":2.295335242,"remaining_time":3.760958273},
{"learn":[498.2922148],"iteration":379,"passed_time":2.299447447,"remaining_time":3.751730045},
{"learn":[498.1139696],"iteration":380,"passed_time":2.304207733,"remaining_time":3.743581592},
{"learn":[498.1113155],"iteration":381,"passed_time":2.309360093,"remaining_time":3.736085177},
{"learn":[497.8084167],"iteration":382,"passed_time":2.315047,"remaining_time":3.729462138},
{"learn":[497.5574067],"iteration":383,"passed_time":2.319909499,"remaining_time":3.721521488},
{"learn":[497.3265641],"iteration":384,"passed_time":2.324793546,"remaining_time":3.713631249},
{"learn":[497.0822742],"iteration":385,"passed_time":2.330428621,"remaining_time":3.706951226},
{"learn":[496.9478574],"iteration":386,"passed_time":2.334970582,"remaining_time":3.698545133},
{"learn":[496.9125086],"iteration":387,"passed_time":2.339308089,"remaining_time":3.68983647},
{"learn":[496.8791417],"iteration":388,"passed_time":2.345393162,"remaining_time":3.683895173},
{"learn":[496.7656057],"iteration":389,"passed_time":2.350288121,"remaining_time":3.676091677},
{"learn":[496.6390566],"iteration":390,"passed_time":2.355114346,"remaining_time":3.668196002},
{"learn":[496.493154],"iteration":391,"passed_time":2.361391959,"remaining_time":3.66256712},
{"learn":[496.4630919],"iteration":392,"passed_time":2.366189838,"remaining_time":3.654649445},
{"learn":[496.2937295],"iteration":393,"passed_time":2.37070202,"remaining_time":3.646308183},
{"learn":[496.1157215],"iteration":394,"passed_time":2.375962739,"remaining_time":3.639132804},
{"learn":[496.012635],"iteration":395,"passed_time":2.381040002,"remaining_time":3.631687275},
{"learn":[495.8741855],"iteration":396,"passed_time":2.385952237,"remaining_time":3.624003019},
{"learn":[495.7218995],"iteration":397,"passed_time":2.391833674,"remaining_time":3.617798673},
{"learn":[495.6200463],"iteration":398,"passed_time":2.396437252,"remaining_time":3.609671149},
{"learn":[495.505935],"iteration":399,"passed_time":2.400853917,"remaining_time":3.601280876},
{"learn":[495.3543122],"iteration":400,"passed_time":2.405384745,"remaining_time":3.593080953},
{"learn":[495.1860711],"iteration":401,"passed_time":2.410291369,"remaining_time":3.585458306},
{"learn":[494.9402805],"iteration":402,"passed_time":2.417111444,"remaining_time":3.580683703},
{"learn":[494.8567011],"iteration":403,"passed_time":2.422614742,"remaining_time":3.573956402},
{"learn":[494.6759302],"iteration":404,"passed_time":2.428484303,"remaining_time":3.567773235},
{"learn":[494.5698753],"iteration":405,"passed_time":2.43258231,"remaining_time":3.558999734},
{"learn":[494.3435812],"iteration":406,"passed_time":2.438043879,"remaining_time":3.552235922},
{"learn":[494.2117756],"iteration":407,"passed_time":2.442872372,"remaining_time":3.544559913},
{"learn":[494.1677123],"iteration":408,"passed_time":2.44708347,"remaining_time":3.536005698},
{"learn":[493.9809758],"iteration":409,"passed_time":2.452314493,"remaining_time":3.528940368},
{"learn":[493.7529733],"iteration":410,"passed_time":2.458034681,"remaining_time":3.522584981},
{"learn":[493.6529721],"iteration":411,"passed_time":2.462977741,"remaining_time":3.515123572},
{"learn":[493.4130985],"iteration":412,"passed_time":2.467948508,"remaining_time":3.50771374},
{"learn":[493.2956149],"iteration":413,"passed_time":2.474176409,"remaining_time":3.50209511},
{"learn":[493.0932704],"iteration":414,"passed_time":2.478971559,"remaining_time":3.494453885},
{"learn":[492.9179428],"iteration":415,"passed_time":2.483503146,"remaining_time":3.486456339},
{"learn":[492.6995018],"iteration":416,"passed_time":2.488942846,"remaining_time":3.479745034},
{"learn":[492.5180772],"iteration":417,"passed_time":2.49477844,"remaining_time":3.473591034},
{"learn":[492.3187164],"iteration":418,"passed_time":2.499452492,"remaining_time":3.465827919},
{"learn":[492.2161049],"iteration":419,"passed_time":2.504276323,"remaining_time":3.458286351},
{"learn":[492.0670222],"iteration":420,"passed_time":2.509685137,"remaining_time":3.451562219},
{"learn":[491.8961074],"iteration":421,"passed_time":2.514192998,"remaining_time":3.443610315},
{"learn":[491.7731168],"iteration":422,"passed_time":2.518897377,"remaining_time":3.435942758},
{"learn":[491.6567153],"iteration":423,"passed_time":2.524575938,"remaining_time":3.429612595},
{"learn":[491.5782888],"iteration":424,"passed_time":2.528406634,"remaining_time":3.420785446},
{"learn":[491.3814805],"iteration":425,"passed_time":2.532540048,"remaining_time":3.412389642},
{"learn":[491.1475899],"iteration":426,"passed_time":2.538326724,"remaining_time":3.406232348},
{"learn":[490.9321412],"iteration":427,"passed_time":2.54352357,"remaining_time":3.39928851},
{"learn":[490.8041207],"iteration":428,"passed_time":2.548112593,"remaining_time":3.391543801},
{"learn":[490.6182069],"iteration":429,"passed_time":2.554061624,"remaining_time":3.385616572},
{"learn":[490.341285],"iteration":430,"passed_time":2.559725143,"remaining_time":3.379312312},
{"learn":[490.1489087],"iteration":431,"passed_time":2.564317572,"remaining_time":3.371602733},
{"learn":[489.9994683],"iteration":432,"passed_time":2.570556867,"remaining_time":3.366064073},
{"learn":[489.7494182],"iteration":433,"passed_time":2.575819903,"remaining_time":3.359248999},
{"learn":[489.5490257],"iteration":434,"passed_time":2.580787715,"remaining_time":3.352057607},
{"learn":[489.4480403],"iteration":435,"passed_time":2.586092082,"remaining_time":3.345311775},
{"learn":[489.2504664],"iteration":436,"passed_time":2.590517117,"remaining_time":3.337439673},
{"learn":[489.1477471],"iteration":437,"passed_time":2.595441966,"remaining_time":3.330224623},
{"learn":[489.0031812],"iteration":438,"passed_time":2.601013557,"remaining_time":3.323846482},
{"learn":[488.8170601],"iteration":439,"passed_time":2.607161502,"remaining_time":3.318205548},
{"learn":[488.5566942],"iteration":440,"passed_time":2.611567767,"remaining_time":3.310354607},
{"learn":[488.3119917],"iteration":441,"passed_time":2.617308306,"remaining_time":3.304203699},
{"learn":[488.2124813],"iteration":442,"passed_time":2.621830776,"remaining_time":3.29652312},
{"learn":[488.0856506],"iteration":443,"passed_time":2.626190681,"remaining_time":3.288653195},
{"learn":[487.8257599],"iteration":444,"passed_time":2.630223925,"remaining_time":3.280391637},
{"learn":[487.5941799],"iteration":445,"passed_time":2.637012205,"remaining_time":3.275571214},
{"learn":[487.56548],"iteration":446,"passed_time":2.64120998,"remaining_time":3.267537179},
{"learn":[487.4900972],"iteration":447,"passed_time":2.645617308,"remaining_time":3.259778469},
{"learn":[487.387922],"iteration":448,"passed_time":2.651641712,"remaining_time":3.254019116},
{"learn":[487.1991761],"iteration":449,"passed_time":2.655834872,"remaining_time":3.246020399},
{"learn":[486.9630934],"iteration":450,"passed_time":2.660356128,"remaining_time":3.238437947},
{"learn":[486.8472744],"iteration":451,"passed_time":2.666739703,"remaining_time":3.233126897},
{"learn":[486.6110473],"iteration":452,"passed_time":2.672264202,"remaining_time":3.226773772},
{"learn":[486.4267987],"iteration":453,"passed_time":2.676966067,"remaining_time":3.219434962},
{"learn":[486.3938699],"iteration":454,"passed_time":2.682379654,"remaining_time":3.212960245},
{"learn":[486.2608248],"iteration":455,"passed_time":2.687632855,"remaining_time":3.206298845},
{"learn":[486.0405815],"iteration":456,"passed_time":2.692401367,"remaining_time":3.199067707},
{"learn":[485.7781141],"iteration":457,"passed_time":2.69806441,"remaining_time":3.192905917},
{"learn":[485.6870962],"iteration":458,"passed_time":2.703617243,"remaining_time":3.186616402},
{"learn":[485.5886686],"iteration":459,"passed_time":2.709066216,"remaining_time":3.180208166},
{"learn":[485.3806413],"iteration":460,"passed_time":2.714290734,"remaining_time":3.173541661},
{"learn":[485.3785646],"iteration":461,"passed_time":2.718629399,"remaining_time":3.165849819},
{"learn":[485.1560141],"iteration":462,"passed_time":2.724018904,"remaining_time":3.159391256},
{"learn":[485.0549976],"iteration":463,"passed_time":2.728394991,"remaining_time":3.151766628},
{"learn":[484.8928428],"iteration":464,"passed_time":2.733839067,"remaining_time":3.145384733},
{"learn":[484.8768743],"iteration":465,"passed_time":2.739588442,"remaining_time":3.139356713},
{"learn":[484.7106412],"iteration":466,"passed_time":2.745321859,"remaining_time":3.133311673},
{"learn":[484.7087439],"iteration":467,"passed_time":2.749682716,"remaining_time":3.125707702},
{"learn":[484.5860629],"iteration":468,"passed_time":2.754625035,"remaining_time":3.118775893},
{"learn":[484.4926133],"iteration":469,"passed_time":2.760280504,"remaining_time":3.112656739},
{"learn":[484.4907894],"iteration":470,"passed_time":2.765812128,"remaining_time":3.106400458},
{"learn":[484.3333425],"iteration":471,"passed_time":2.770087071,"remaining_time":3.098741469},
{"learn":[484.3280509],"iteration":472,"passed_time":2.774136928,"remaining_time":3.090846006},
{"learn":[484.3263778],"iteration":473,"passed_time":2.77988228,"remaining_time":3.084848269},
{"learn":[484.3247737],"iteration":474,"passed_time":2.784002723,"remaining_time":3.077055641},
{"learn":[484.0737051],"iteration":475,"passed_time":2.788306824,"remaining_time":3.069480621},
{"learn":[484.045111],"iteration":476,"passed_time":2.792923979,"remaining_time":3.06226256},
{"learn":[484.0435705],"iteration":477,"passed_time":2.798540999,"remaining_time":3.056147283},
{"learn":[483.8006361],"iteration":478,"passed_time":2.803573941,"remaining_time":3.049398796},
{"learn":[483.7901513],"iteration":479,"passed_time":2.808034633,"remaining_time":3.042037519},
{"learn":[483.7512891],"iteration":480,"passed_time":2.815500328,"remaining_time":3.037930707},
{"learn":[483.5353379],"iteration":481,"passed_time":2.820351256,"remaining_time":3.030999898},
{"learn":[483.3608179],"iteration":482,"passed_time":2.825115324,"remaining_time":3.023984725},
{"learn":[483.3560523],"iteration":483,"passed_time":2.829954501,"remaining_time":3.017058931},
{"learn":[483.2282222],"iteration":484,"passed_time":2.835560657,"remaining_time":3.010956162},
{"learn":[483.0036972],"iteration":485,"passed_time":2.839939243,"remaining_time":3.003557141},
{"learn":[482.9090577],"iteration":486,"passed_time":2.845116093,"remaining_time":2.997011408},
{"learn":[482.7562048],"iteration":487,"passed_time":2.850852829,"remaining_time":2.991058706},
{"learn":[482.7001651],"iteration":488,"passed_time":2.855647448,"remaining_time":2.984122384},
{"learn":[482.5463184],"iteration":489,"passed_time":2.861228146,"remaining_time":2.978012968},
{"learn":[482.4917606],"iteration":490,"passed_time":2.866184855,"remaining_time":2.971258841},
{"learn":[482.3011559],"iteration":491,"passed_time":2.870274519,"remaining_time":2.963616779},
{"learn":[482.28887],"iteration":492,"passed_time":2.874907003,"remaining_time":2.956547364},
{"learn":[482.2070023],"iteration":493,"passed_time":2.880300065,"remaining_time":2.950266868},
{"learn":[482.0242547],"iteration":494,"passed_time":2.885158144,"remaining_time":2.943444167},
{"learn":[481.899743],"iteration":495,"passed_time":2.890321748,"remaining_time":2.936939841},
{"learn":[481.7103567],"iteration":496,"passed_time":2.895227327,"remaining_time":2.93017977},
{"learn":[481.6360337],"iteration":497,"passed_time":2.900292044,"remaining_time":2.923587562},
{"learn":[481.4930057],"iteration":498,"passed_time":2.906120911,"remaining_time":2.91776869},
{"learn":[481.2782562],"iteration":499,"passed_time":2.911633002,"remaining_time":2.911633002},
{"learn":[481.1091583],"iteration":500,"passed_time":2.916470975,"remaining_time":2.904828376},
{"learn":[481.0406887],"iteration":501,"passed_time":2.920923088,"remaining_time":2.897648801},
{"learn":[481.0154932],"iteration":502,"passed_time":2.926291019,"remaining_time":2.891384963},
{"learn":[481.0140628],"iteration":503,"passed_time":2.930833777,"remaining_time":2.884312605},
{"learn":[480.8383048],"iteration":504,"passed_time":2.935199515,"remaining_time":2.877076753},
{"learn":[480.7583096],"iteration":505,"passed_time":2.94126374,"remaining_time":2.87151045},
{"learn":[480.6273771],"iteration":506,"passed_time":2.945958755,"remaining_time":2.864610781},
{"learn":[480.5723604],"iteration":507,"passed_time":2.950342569,"remaining_time":2.857418394},
{"learn":[480.3947854],"iteration":508,"passed_time":2.956745921,"remaining_time":2.852185161},
{"learn":[480.2404197],"iteration":509,"passed_time":2.961642583,"remaining_time":2.845499737},
{"learn":[480.0169295],"iteration":510,"passed_time":2.965809354,"remaining_time":2.838122846},
{"learn":[479.9299508],"iteration":511,"passed_time":2.971298854,"remaining_time":2.832019221},
{"learn":[479.7149755],"iteration":512,"passed_time":2.976680221,"remaining_time":2.825815337},
{"learn":[479.6261767],"iteration":513,"passed_time":2.981367752,"remaining_time":2.818958613},
{"learn":[479.6040636],"iteration":514,"passed_time":2.98591436,"remaining_time":2.811977601},
{"learn":[479.4805153],"iteration":515,"passed_time":2.99173563,"remaining_time":2.806201638},
{"learn":[479.3319815],"iteration":516,"passed_time":2.996841044,"remaining_time":2.79975672},
{"learn":[479.2727436],"iteration":517,"passed_time":3.001531778,"remaining_time":2.792931114},
{"learn":[479.270931],"iteration":518,"passed_time":3.006888206,"remaining_time":2.786730688},
{"learn":[479.1758117],"iteration":519,"passed_time":3.01151756,"remaining_time":2.779862363},
{"learn":[479.0546183],"iteration":520,"passed_time":3.016382935,"remaining_time":2.773219627},
{"learn":[479.0511093],"iteration":521,"passed_time":3.020761712,"remaining_time":2.766138119},
{"learn":[478.8853061],"iteration":522,"passed_time":3.026178787,"remaining_time":2.760013922},
{"learn":[478.8339659],"iteration":523,"passed_time":3.030206915,"remaining_time":2.752630709},
{"learn":[478.6923923],"iteration":524,"passed_time":3.036105712,"remaining_time":2.746952787},
{"learn":[478.6567322],"iteration":525,"passed_time":3.041663114,"remaining_time":2.740966381},
{"learn":[478.5990628],"iteration":526,"passed_time":3.046132776,"remaining_time":2.734005319},
{"learn":[478.5131621],"iteration":527,"passed_time":3.05149272,"remaining_time":2.727849553},
{"learn":[478.3150229],"iteration":528,"passed_time":3.056868543,"remaining_time":2.721710934},
{"learn":[478.165643],"iteration":529,"passed_time":3.06092013,"remaining_time":2.71440087},
{"learn":[477.9539536],"iteration":530,"passed_time":3.065813247,"remaining_time":2.707846352},
{"learn":[477.8861257],"iteration":531,"passed_time":3.071559697,"remaining_time":2.702048756},
{"learn":[477.8077471],"iteration":532,"passed_time":3.076340839,"remaining_time":2.695405576},
{"learn":[477.8060275],"iteration":533,"passed_time":3.080622763,"remaining_time":2.688333722},
{"learn":[477.7639196],"iteration":534,"passed_time":3.085395438,"remaining_time":2.681698839},
{"learn":[477.5598763],"iteration":535,"passed_time":3.090809406,"remaining_time":2.675626053},
{"learn":[477.3368399],"iteration":536,"passed_time":3.095666573,"remaining_time":2.669075648},
{"learn":[477.2392563],"iteration":537,"passed_time":3.100566769,"remaining_time":2.66256849},
{"learn":[477.0801804],"iteration":538,"passed_time":3.106089024,"remaining_time":2.656599333},
{"learn":[476.956713],"iteration":539,"passed_time":3.111335512,"remaining_time":2.650396918},
{"learn":[476.8493127],"iteration":540,"passed_time":3.116339661,"remaining_time":2.64399243},
{"learn":[476.7595058],"iteration":541,"passed_time":3.122007007,"remaining_time":2.638153522},
{"learn":[476.6250215],"iteration":542,"passed_time":3.12632371,"remaining_time":2.631178518},
{"learn":[476.5116111],"iteration":543,"passed_time":3.130370014,"remaining_time":2.623986629},
{"learn":[476.4382386],"iteration":544,"passed_time":3.136147981,"remaining_time":2.618251985},
{"learn":[476.40019],"iteration":545,"passed_time":3.141644181,"remaining_time":2.61228289},
{"learn":[476.3832881],"iteration":546,"passed_time":3.145830881,"remaining_time":2.605231058},
{"learn":[476.2218057],"iteration":547,"passed_time":3.152083074,"remaining_time":2.599893338},
{"learn":[476.0855638],"iteration":548,"passed_time":3.156175098,"remaining_time":2.592777721},
{"learn":[475.9822447],"iteration":549,"passed_time":3.160285371,"remaining_time":2.585688031},
{"learn":[475.869328],"iteration":550,"passed_time":3.165467832,"remaining_time":2.579482861},
{"learn":[475.6842747],"iteration":551,"passed_time":3.170847413,"remaining_time":2.573441378},
{"learn":[475.5535916],"iteration":552,"passed_time":3.176007852,"remaining_time":2.567225153},
{"learn":[475.5217848],"iteration":553,"passed_time":3.180710945,"remaining_time":2.560644551},
{"learn":[475.4196474],"iteration":554,"passed_time":3.187161147,"remaining_time":2.555471551},
{"learn":[475.325865],"iteration":555,"passed_time":3.19169273,"remaining_time":2.54876182},
{"learn":[475.2442918],"iteration":556,"passed_time":3.196388611,"remaining_time":2.542190583},
{"learn":[475.1749701],"iteration":557,"passed_time":3.204614759,"remaining_time":2.538422444},
{"learn":[474.965481],"iteration":558,"passed_time":3.209033985,"remaining_time":2.53163504},
{"learn":[474.8016927],"iteration":559,"passed_time":3.214770842,"remaining_time":2.525891376},
{"learn":[474.6980089],"iteration":560,"passed_time":3.221397516,"remaining_time":2.520844045},
{"learn":[474.5929073],"iteration":561,"passed_time":3.226569526,"remaining_time":2.514657388},
{"learn":[474.5914894],"iteration":562,"passed_time":3.231540016,"remaining_time":2.508317917},
{"learn":[474.4699624],"iteration":563,"passed_time":3.236666461,"remaining_time":2.50210386},
{"learn":[474.356204],"iteration":564,"passed_time":3.242797077,"remaining_time":2.496666776},
{"learn":[474.287782],"iteration":565,"passed_time":3.249147427,"remaining_time":2.49139573},
{"learn":[474.1733712],"iteration":566,"passed_time":3.254720165,"remaining_time":2.48552704},
{"learn":[474.1719998],"iteration":567,"passed_time":3.25907241,"remaining_time":2.478731129},
{"learn":[474.0851789],"iteration":568,"passed_time":3.265405906,"remaining_time":2.473444544},
{"learn":[474.0706192],"iteration":569,"passed_time":3.270041157,"remaining_time":2.466873153},
{"learn":[473.925683],"iteration":570,"passed_time":3.274579936,"remaining_time":2.460236064},
{"learn":[473.7305749],"iteration":571,"passed_time":3.279689181,"remaining_time":2.454033163},
{"learn":[473.5825783],"iteration":572,"passed_time":3.284823734,"remaining_time":2.44785294},
{"learn":[473.4372869],"iteration":573,"passed_time":3.289146859,"remaining_time":2.44107415},
{"learn":[473.3218395],"iteration":574,"passed_time":3.293994492,"remaining_time":2.434691581},
{"learn":[473.2859182],"iteration":575,"passed_time":3.299823892,"remaining_time":2.429037032},
{"learn":[473.1922786],"iteration":576,"passed_time":3.304140725,"remaining_time":2.42227301},
{"learn":[473.137836],"iteration":577,"passed_time":3.308603103,"remaining_time":2.415623719},
{"learn":[473.0691677],"iteration":578,"passed_time":3.31529538,"remaining_time":2.410603376},
{"learn":[472.8897078],"iteration":579,"passed_time":3.321222906,"remaining_time":2.405023483},
{"learn":[472.7934212],"iteration":580,"passed_time":3.326528694,"remaining_time":2.398994015},
{"learn":[472.6664342],"iteration":581,"passed_time":3.332335708,"remaining_time":2.39332702},
{"learn":[472.5852455],"iteration":582,"passed_time":3.337298526,"remaining_time":2.387055721},
{"learn":[472.4544836],"iteration":583,"passed_time":3.34167377,"remaining_time":2.380370357},
{"learn":[472.4342444],"iteration":584,"passed_time":3.347795254,"remaining_time":2.374931676},
{"learn":[472.2837634],"iteration":585,"passed_time":3.352047752,"remaining_time":2.368170255},
{"learn":[472.1829692],"iteration":586,"passed_time":3.356236971,"remaining_time":2.36137286},
{"learn":[472.0344953],"iteration":587,"passed_time":3.361873448,"remaining_time":2.355598402},
{"learn":[471.936133],"iteration":588,"passed_time":3.366283623,"remaining_time":2.348968708},
{"learn":[471.7568744],"iteration":589,"passed_time":3.370767941,"remaining_time":2.342398061},
{"learn":[471.6380972],"iteration":590,"passed_time":3.375500306,"remaining_time":2.336006134},
{"learn":[471.636355],"iteration":591,"passed_time":3.380711344,"remaining_time":2.32994971},
{"learn":[471.4686462],"iteration":592,"passed_time":3.384790318,"remaining_time":2.323119156},
{"learn":[471.3472182],"iteration":593,"passed_time":3.389138352,"remaining_time":2.316481769},
{"learn":[471.2164946],"iteration":594,"passed_time":3.39595795,"remaining_time":2.311534403},
{"learn":[471.1984147],"iteration":595,"passed_time":3.400324788,"remaining_time":2.304918145},
{"learn":[471.0297424],"iteration":596,"passed_time":3.404369906,"remaining_time":2.298092248},
{"learn":[470.9025081],"iteration":597,"passed_time":3.411331401,"remaining_time":2.293236159},
{"learn":[470.8455594],"iteration":598,"passed_time":3.417126231,"remaining_time":2.287592018},
{"learn":[470.6933403],"iteration":599,"passed_time":3.423188663,"remaining_time":2.282125776},
{"learn":[470.6357304],"iteration":600,"passed_time":3.428581787,"remaining_time":2.2762132},
{"learn":[470.5608529],"iteration":601,"passed_time":3.433210726,"remaining_time":2.269797125},
{"learn":[470.5297405],"iteration":602,"passed_time":3.437563477,"remaining_time":2.263205141},
{"learn":[470.3464368],"iteration":603,"passed_time":3.444105015,"remaining_time":2.258055606},
{"learn":[470.318967],"iteration":604,"passed_time":3.448200853,"remaining_time":2.251304689},
{"learn":[470.1975588],"iteration":605,"passed_time":3.453311482,"remaining_time":2.245222317},
{"learn":[470.1784796],"iteration":606,"passed_time":3.459590018,"remaining_time":2.239899303},
{"learn":[470.1093504],"iteration":607,"passed_time":3.464131221,"remaining_time":2.233453024},
{"learn":[470.0328589],"iteration":608,"passed_time":3.468634194,"remaining_time":2.226988457},
{"learn":[469.9093897],"iteration":609,"passed_time":3.474533298,"remaining_time":2.221422928},
{"learn":[469.7922595],"iteration":610,"passed_time":3.478863499,"remaining_time":2.214857448},
{"learn":[469.7707122],"iteration":611,"passed_time":3.483527004,"remaining_time":2.208510584},
{"learn":[469.7473552],"iteration":612,"passed_time":3.488342954,"remaining_time":2.202265454},
{"learn":[469.7304707],"iteration":613,"passed_time":3.493653362,"remaining_time":2.196335827},
{"learn":[469.6158273],"iteration":614,"passed_time":3.498096918,"remaining_time":2.18986555},
{"learn":[469.6145639],"iteration":615,"passed_time":3.502007655,"remaining_time":2.183069707},
{"learn":[469.4759184],"iteration":616,"passed_time":3.508208441,"remaining_time":2.177704753},
{"learn":[469.4179319],"iteration":617,"passed_time":3.512566941,"remaining_time":2.171198336},
{"learn":[469.3428056],"iteration":618,"passed_time":3.518327148,"remaining_time":2.165561621},
{"learn":[469.2241611],"iteration":619,"passed_time":3.524265765,"remaining_time":2.160033856},
{"learn":[469.1134776],"iteration":620,"passed_time":3.530148567,"remaining_time":2.154470704},
{"learn":[469.0986908],"iteration":621,"passed_time":3.534252832,"remaining_time":2.147825676},
{"learn":[469.0851144],"iteration":622,"passed_time":3.540659177,"remaining_time":2.142581877},
{"learn":[468.9871285],"iteration":623,"passed_time":3.545492515,"remaining_time":2.136386515},
{"learn":[468.9594658],"iteration":624,"passed_time":3.549713398,"remaining_time":2.129828039},
{"learn":[468.9366051],"iteration":625,"passed_time":3.556287645,"remaining_time":2.124683034},
{"learn":[468.7834165],"iteration":626,"passed_time":3.560761318,"remaining_time":2.118283846},
{"learn":[468.7120018],"iteration":627,"passed_time":3.56605938,"remaining_time":2.112379123},
{"learn":[468.6448123],"iteration":628,"passed_time":3.571717848,"remaining_time":2.106688905},
{"learn":[468.5303363],"iteration":629,"passed_time":3.576841771,"remaining_time":2.10068485},
{"learn":[468.4466862],"iteration":630,"passed_time":3.581730617,"remaining_time":2.094546114},
{"learn":[468.3293665],"iteration":631,"passed_time":3.587169739,"remaining_time":2.088731747},
{"learn":[468.295525],"iteration":632,"passed_time":3.591572944,"remaining_time":2.082317963},
{"learn":[468.2321184],"iteration":633,"passed_time":3.598051402,"remaining_time":2.077108538},
{"learn":[468.1113601],"iteration":634,"passed_time":3.60411472,"remaining_time":2.071656492},
{"learn":[468.1002338],"iteration":635,"passed_time":3.608552917,"remaining_time":2.065272424},
{"learn":[468.0815024],"iteration":636,"passed_time":3.613609697,"remaining_time":2.05924697},
{"learn":[468.0695003],"iteration":637,"passed_time":3.618688505,"remaining_time":2.053237052},
{"learn":[468.0535989],"iteration":638,"passed_time":3.623601018,"remaining_time":2.0471361},
{"learn":[467.8903251],"iteration":639,"passed_time":3.629072073,"remaining_time":2.041353041},
{"learn":[467.7779331],"iteration":640,"passed_time":3.633893294,"remaining_time":2.035207008},
{"learn":[467.6876284],"iteration":641,"passed_time":3.639500509,"remaining_time":2.029503399},
{"learn":[467.5850692],"iteration":642,"passed_time":3.645340348,"remaining_time":2.023929245},
{"learn":[467.5543075],"iteration":643,"passed_time":3.650370046,"remaining_time":2.017906423},
{"learn":[467.4705886],"iteration":644,"passed_time":3.655814946,"remaining_time":2.012115203},
{"learn":[467.3991551],"iteration":645,"passed_time":3.66009882,"remaining_time":2.005688827},
{"learn":[467.3687227],"iteration":646,"passed_time":3.66457896,"remaining_time":1.999376156},
{"learn":[467.1441002],"iteration":647,"passed_time":3.670339251,"remaining_time":1.993764531},
{"learn":[467.0290041],"iteration":648,"passed_time":3.675105826,"remaining_time":1.987615015},
{"learn":[467.0007761],"iteration":649,"passed_time":3.679796344,"remaining_time":1.981428801},
{"learn":[466.9602343],"iteration":650,"passed_time":3.685527824,"remaining_time":1.975805239},
{"learn":[466.8723311],"iteration":651,"passed_time":3.690400815,"remaining_time":1.969723135},
{"learn":[466.7779114],"iteration":652,"passed_time":3.695079295,"remaining_time":1.963541371},
{"learn":[466.7070986],"iteration":653,"passed_time":3.700455357,"remaining_time":1.957733263},
{"learn":[466.6219997],"iteration":654,"passed_time":3.705406936,"remaining_time":1.95170289},
{"learn":[466.4931401],"iteration":655,"passed_time":3.710202736,"remaining_time":1.945594118},
{"learn":[466.4369892],"iteration":656,"passed_time":3.71542218,"remaining_time":1.939710514},
{"learn":[466.2991576],"iteration":657,"passed_time":3.720944608,"remaining_time":1.933986407},
{"learn":[466.1885549],"iteration":658,"passed_time":3.72705777,"remaining_time":1.928568588},
{"learn":[466.0577154],"iteration":659,"passed_time":3.73341146,"remaining_time":1.92327257},
{"learn":[465.9214872],"iteration":660,"passed_time":3.738851218,"remaining_time":1.917504634},
{"learn":[465.8663493],"iteration":661,"passed_time":3.744884272,"remaining_time":1.91204061},
{"learn":[465.8134101],"iteration":662,"passed_time":3.751615055,"remaining_time":1.906929522},
{"learn":[465.7710444],"iteration":663,"passed_time":3.756577786,"remaining_time":1.90091888},
{"learn":[465.7238649],"iteration":664,"passed_time":3.760817731,"remaining_time":1.894547278},
{"learn":[465.6413629],"iteration":665,"passed_time":3.766741225,"remaining_time":1.88902638},
{"learn":[465.6132833],"iteration":666,"passed_time":3.771231932,"remaining_time":1.882788955},
{"learn":[465.4997562],"iteration":667,"passed_time":3.775735544,"remaining_time":1.876563175},
{"learn":[465.2532317],"iteration":668,"passed_time":3.78202478,"remaining_time":1.871226012},
{"learn":[465.0843815],"iteration":669,"passed_time":3.786618512,"remaining_time":1.865050909},
{"learn":[465.0114617],"iteration":670,"passed_time":3.791414151,"remaining_time":1.858979516},
{"learn":[464.9394674],"iteration":671,"passed_time":3.797869753,"remaining_time":1.853722142},
{"learn":[464.8819238],"iteration":672,"passed_time":3.802600834,"remaining_time":1.847623288},
{"learn":[464.7788078],"iteration":673,"passed_time":3.808162387,"remaining_time":1.841930175},
{"learn":[464.7148222],"iteration":674,"passed_time":3.814051031,"remaining_time":1.836394941},
{"learn":[464.58816],"iteration":675,"passed_time":3.819081861,"remaining_time":1.830447519},
{"learn":[464.4829243],"iteration":676,"passed_time":3.823442506,"remaining_time":1.824183057},
{"learn":[464.3364488],"iteration":677,"passed_time":3.828583259,"remaining_time":1.818294704},
{"learn":[464.2571746],"iteration":678,"passed_time":3.834096436,"remaining_time":1.812584618},
{"learn":[464.2060459],"iteration":679,"passed_time":3.839389376,"remaining_time":1.806771471},
{"learn":[464.0693218],"iteration":680,"passed_time":3.845263873,"remaining_time":1.80123227},
{"learn":[464.0085075],"iteration":681,"passed_time":3.850318132,"remaining_time":1.795309627},
{"learn":[463.8949596],"iteration":682,"passed_time":3.855059341,"remaining_time":1.789244233},
{"learn":[463.7815695],"iteration":683,"passed_time":3.860034132,"remaining_time":1.783290622},
{"learn":[463.6828883],"iteration":684,"passed_time":3.86550968,"remaining_time":1.777570145},
{"learn":[463.6200176],"iteration":685,"passed_time":3.870813824,"remaining_time":1.771771925},
{"learn":[463.5283365],"iteration":686,"passed_time":3.876491467,"remaining_time":1.766145312},
{"learn":[463.4425647],"iteration":687,"passed_time":3.882163336,"remaining_time":1.760515931},
{"learn":[463.2446013],"iteration":688,"passed_time":3.886191521,"remaining_time":1.754144504},
{"learn":[463.1596947],"iteration":689,"passed_time":3.890985586,"remaining_time":1.748123959},
{"learn":[463.1048294],"iteration":690,"passed_time":3.896632667,"remaining_time":1.742488414},
{"learn":[463.0640821],"iteration":691,"passed_time":3.902007097,"remaining_time":1.736731483},
{"learn":[462.9974345],"iteration":692,"passed_time":3.905839807,"remaining_time":1.73029267},
{"learn":[462.8170493],"iteration":693,"passed_time":3.911212134,"remaining_time":1.724540221},
{"learn":[462.7705206],"iteration":694,"passed_time":3.917552869,"remaining_time":1.719213849},
{"learn":[462.6695839],"iteration":695,"passed_time":3.922051344,"remaining_time":1.713079897},
{"learn":[462.5712788],"iteration":696,"passed_time":3.928179041,"remaining_time":1.707658894},
{"learn":[462.4304434],"iteration":697,"passed_time":3.93290977,"remaining_time":1.701631448},
{"learn":[462.3319337],"iteration":698,"passed_time":3.936935161,"remaining_time":1.695303982},
{"learn":[462.2630104],"iteration":699,"passed_time":3.943121033,"remaining_time":1.689909014},
{"learn":[462.1077166],"iteration":700,"passed_time":3.948537025,"remaining_time":1.68418341},
{"learn":[461.9314544],"iteration":701,"passed_time":3.953689964,"remaining_time":1.678347022},
{"learn":[461.8273904],"iteration":702,"passed_time":3.960076296,"remaining_time":1.673033656},
{"learn":[461.7293983],"iteration":703,"passed_time":3.965522248,"remaining_time":1.667321854},
{"learn":[461.52742],"iteration":704,"passed_time":3.970051816,"remaining_time":1.661227355},
{"learn":[461.3837094],"iteration":705,"passed_time":3.975996867,"remaining_time":1.655726741},
{"learn":[461.2619268],"iteration":706,"passed_time":3.980879271,"remaining_time":1.649784479},
{"learn":[461.1486567],"iteration":707,"passed_time":3.98528238,"remaining_time":1.643647535},
{"learn":[461.1259694],"iteration":708,"passed_time":3.991892644,"remaining_time":1.638421381},
{"learn":[461.1051425],"iteration":709,"passed_time":4.002336403,"remaining_time":1.634757123},
{"learn":[461.0179254],"iteration":710,"passed_time":4.011853498,"remaining_time":1.630697132},
{"learn":[461.0169046],"iteration":711,"passed_time":4.017022796,"remaining_time":1.624863153},
{"learn":[461.0159276],"iteration":712,"passed_time":4.023442973,"remaining_time":1.619534549},
{"learn":[460.9249514],"iteration":713,"passed_time":4.028417238,"remaining_time":1.613623712},
{"learn":[460.7668051],"iteration":714,"passed_time":4.033211712,"remaining_time":1.607643829},
{"learn":[460.6860569],"iteration":715,"passed_time":4.039911823,"remaining_time":1.602423125},
{"learn":[460.5518211],"iteration":716,"passed_time":4.04453623,"remaining_time":1.596379014},
{"learn":[460.5485328],"iteration":717,"passed_time":4.049111885,"remaining_time":1.59031971},
{"learn":[460.5361927],"iteration":718,"passed_time":4.05399657,"remaining_time":1.584385308},
{"learn":[460.4277129],"iteration":719,"passed_time":4.059291295,"remaining_time":1.578613281},
{"learn":[460.3513664],"iteration":720,"passed_time":4.064948605,"remaining_time":1.572982886},
{"learn":[460.2759037],"iteration":721,"passed_time":4.069876185,"remaining_time":1.56707144},
{"learn":[460.186946],"iteration":722,"passed_time":4.07510146,"remaining_time":1.56127677},
{"learn":[460.0009693],"iteration":723,"passed_time":4.079655083,"remaining_time":1.555227628},
{"learn":[459.975849],"iteration":724,"passed_time":4.083996292,"remaining_time":1.549102042},
{"learn":[459.9165415],"iteration":725,"passed_time":4.090757422,"remaining_time":1.543894675},
{"learn":[459.9066609],"iteration":726,"passed_time":4.095022521,"remaining_time":1.537745733},
{"learn":[459.8234107],"iteration":727,"passed_time":4.099266408,"remaining_time":1.531594043},
{"learn":[459.698803],"iteration":728,"passed_time":4.105563042,"remaining_time":1.526210678},
{"learn":[459.592997],"iteration":729,"passed_time":4.109854826,"remaining_time":1.520083292},
{"learn":[459.5268548],"iteration":730,"passed_time":4.115220749,"remaining_time":1.514356199},
{"learn":[459.4134815],"iteration":731,"passed_time":4.121752304,"remaining_time":1.509056854},
{"learn":[459.3558354],"iteration":732,"passed_time":4.126201431,"remaining_time":1.50299561},
{"learn":[459.2596776],"iteration":733,"passed_time":4.131220698,"remaining_time":1.497145375},
{"learn":[459.1673946],"iteration":734,"passed_time":4.13727646,"remaining_time":1.491671105},
{"learn":[459.0318039],"iteration":735,"passed_time":4.142011138,"remaining_time":1.485721386},
{"learn":[458.8621957],"iteration":736,"passed_time":4.146387764,"remaining_time":1.479647194},
{"learn":[458.8011763],"iteration":737,"passed_time":4.153349928,"remaining_time":1.474495503},
{"learn":[458.6713473],"iteration":738,"passed_time":4.158116119,"remaining_time":1.468563338},
{"learn":[458.5995456],"iteration":739,"passed_time":4.162755059,"remaining_time":1.462589615},
{"learn":[458.5416357],"iteration":740,"passed_time":4.168441221,"remaining_time":1.456985528},
{"learn":[458.3841068],"iteration":741,"passed_time":4.174033128,"remaining_time":1.451348446},
{"learn":[458.3201082],"iteration":742,"passed_time":4.178085787,"remaining_time":1.445179068},
{"learn":[458.2962758],"iteration":743,"passed_time":4.184525564,"remaining_time":1.439836753},
{"learn":[458.2449053],"iteration":744,"passed_time":4.188815853,"remaining_time":1.433755762},
{"learn":[458.2022067],"iteration":745,"passed_time":4.193184335,"remaining_time":1.427706195},
{"learn":[458.1192879],"iteration":746,"passed_time":4.198842625,"remaining_time":1.422097971},
{"learn":[458.0020588],"iteration":747,"passed_time":4.204812375,"remaining_time":1.416594543},
{"learn":[457.9093931],"iteration":748,"passed_time":4.210032796,"remaining_time":1.410838761},
{"learn":[457.7888299],"iteration":749,"passed_time":4.216098175,"remaining_time":1.405366058},
{"learn":[457.7220145],"iteration":750,"passed_time":4.220723761,"remaining_time":1.399414403},
{"learn":[457.5997416],"iteration":751,"passed_time":4.225256647,"remaining_time":1.393435703},
{"learn":[457.4185949],"iteration":752,"passed_time":4.23107775,"remaining_time":1.387883405},
{"learn":[457.3621022],"iteration":753,"passed_time":4.235463436,"remaining_time":1.381862076},
{"learn":[457.3129285],"iteration":754,"passed_time":4.240203653,"remaining_time":1.375960126},
{"learn":[457.1252636],"iteration":755,"passed_time":4.246076639,"remaining_time":1.370426852},
{"learn":[456.9988906],"iteration":756,"passed_time":4.251660975,"remaining_time":1.364800022},
{"learn":[456.9073055],"iteration":757,"passed_time":4.257930464,"remaining_time":1.359392048},
{"learn":[456.8123672],"iteration":758,"passed_time":4.263478482,"remaining_time":1.353752719},
{"learn":[456.7909696],"iteration":759,"passed_time":4.268483258,"remaining_time":1.347942081},
{"learn":[456.7040524],"iteration":760,"passed_time":4.273502697,"remaining_time":1.342138166},
{"learn":[456.6602181],"iteration":761,"passed_time":4.279089002,"remaining_time":1.336513363},
{"learn":[456.5853047],"iteration":762,"passed_time":4.284347327,"remaining_time":1.330786784},
{"learn":[456.4541198],"iteration":763,"passed_time":4.289956479,"remaining_time":1.325169802},
{"learn":[456.4077245],"iteration":764,"passed_time":4.2951803,"remaining_time":1.319434471},
{"learn":[456.2902164],"iteration":765,"passed_time":4.300545769,"remaining_time":1.313743747},
{"learn":[456.2241015],"iteration":766,"passed_time":4.306761281,"remaining_time":1.308312097},
{"learn":[456.1061264],"iteration":767,"passed_time":4.311528252,"remaining_time":1.302440826},
{"learn":[456.0421223],"iteration":768,"passed_time":4.316149668,"remaining_time":1.296528704},
{"learn":[455.9963299],"iteration":769,"passed_time":4.321320568,"remaining_time":1.290784066},
{"learn":[455.8997853],"iteration":770,"passed_time":4.326737536,"remaining_time":1.285114002},
{"learn":[455.7647602],"iteration":771,"passed_time":4.332366878,"remaining_time":1.279507316},
{"learn":[455.6372877],"iteration":772,"passed_time":4.337959017,"remaining_time":1.273889647},
{"learn":[455.5852915],"iteration":773,"passed_time":4.343309324,"remaining_time":1.26820143},
{"learn":[455.4350965],"iteration":774,"passed_time":4.348541366,"remaining_time":1.262479751},
{"learn":[455.2826564],"iteration":775,"passed_time":4.353277677,"remaining_time":1.256616237},
{"learn":[455.250393],"iteration":776,"passed_time":4.357765129,"remaining_time":1.2506842},
{"learn":[455.2175598],"iteration":777,"passed_time":4.363140263,"remaining_time":1.245009175},
{"learn":[455.0944983],"iteration":778,"passed_time":4.368271634,"remaining_time":1.239265765},
{"learn":[455.0470633],"iteration":779,"passed_time":4.372892052,"remaining_time":1.233379809},
{"learn":[455.0290188],"iteration":780,"passed_time":4.380343764,"remaining_time":1.228291017},
{"learn":[454.9364655],"iteration":781,"passed_time":4.385581671,"remaining_time":1.222579034},
{"learn":[454.8354036],"iteration":782,"passed_time":4.391813973,"remaining_time":1.217143847},
{"learn":[454.7300984],"iteration":783,"passed_time":4.397792424,"remaining_time":1.211636688},
{"learn":[454.5897379],"iteration":784,"passed_time":4.402391684,"remaining_time":1.205750589},
{"learn":[454.5202054],"iteration":785,"passed_time":4.406988909,"remaining_time":1.199867209},
{"learn":[454.3432812],"iteration":786,"passed_time":4.412428449,"remaining_time":1.194215069},
{"learn":[454.2980793],"iteration":787,"passed_time":4.417193134,"remaining_time":1.188381909},
{"learn":[454.1512677],"iteration":788,"passed_time":4.421545683,"remaining_time":1.182441241},
{"learn":[454.0282086],"iteration":789,"passed_time":4.426982525,"remaining_time":1.176792823},
{"learn":[453.8789854],"iteration":790,"passed_time":4.432504461,"remaining_time":1.171167424},
{"learn":[453.8332267],"iteration":791,"passed_time":4.436977294,"remaining_time":1.165266764},
{"learn":[453.7481504],"iteration":792,"passed_time":4.442440907,"remaining_time":1.159628333},
{"learn":[453.648657],"iteration":793,"passed_time":4.448326199,"remaining_time":1.154099744},
{"learn":[453.5467412],"iteration":794,"passed_time":4.453393757,"remaining_time":1.148359396},
{"learn":[453.4954633],"iteration":795,"passed_time":4.458562594,"remaining_time":1.142646695},
{"learn":[453.3890891],"iteration":796,"passed_time":4.464165453,"remaining_time":1.137045906},
{"learn":[453.3325102],"iteration":797,"passed_time":4.468533414,"remaining_time":1.131132518},
{"learn":[453.2205939],"iteration":798,"passed_time":4.473306244,"remaining_time":1.12532485},
{"learn":[453.1162161],"iteration":799,"passed_time":4.478860888,"remaining_time":1.119715222},
{"learn":[452.9777926],"iteration":800,"passed_time":4.484070075,"remaining_time":1.114019906},
{"learn":[452.8202763],"iteration":801,"passed_time":4.489095614,"remaining_time":1.108280463},
{"learn":[452.7597529],"iteration":802,"passed_time":4.495433441,"remaining_time":1.102864742},
{"learn":[452.7042178],"iteration":803,"passed_time":4.500167999,"remaining_time":1.09705588},
{"learn":[452.5704696],"iteration":804,"passed_time":4.50518534,"remaining_time":1.091318188},
{"learn":[452.4549465],"iteration":805,"passed_time":4.512035934,"remaining_time":1.086023537},
{"learn":[452.3083276],"iteration":806,"passed_time":4.516490339,"remaining_time":1.080151965},
{"learn":[452.2542356],"iteration":807,"passed_time":4.52118722,"remaining_time":1.074341518},
{"learn":[452.1295622],"iteration":808,"passed_time":4.526974025,"remaining_time":1.068791148},
{"learn":[452.1026236],"iteration":809,"passed_time":4.531128176,"remaining_time":1.062857227},
{"learn":[452.0232473],"iteration":810,"passed_time":4.535432539,"remaining_time":1.0569627},
{"learn":[451.866869],"iteration":811,"passed_time":4.541416183,"remaining_time":1.05146089},
{"learn":[451.8418368],"iteration":812,"passed_time":4.545495607,"remaining_time":1.0455199},
{"learn":[451.6384012],"iteration":813,"passed_time":4.55019184,"remaining_time":1.039724425},
{"learn":[451.4819597],"iteration":814,"passed_time":4.556593908,"remaining_time":1.034318863},
{"learn":[451.4114834],"iteration":815,"passed_time":4.560633729,"remaining_time":1.028378194},
{"learn":[451.3601697],"iteration":816,"passed_time":4.564993978,"remaining_time":1.022513951},
{"learn":[451.329565],"iteration":817,"passed_time":4.570535048,"remaining_time":1.016916111},
{"learn":[451.2451023],"iteration":818,"passed_time":4.576522056,"remaining_time":1.011416962},
{"learn":[451.1201355],"iteration":819,"passed_time":4.580955598,"remaining_time":1.005575619},
{"learn":[451.0344457],"iteration":820,"passed_time":4.585977837,"remaining_time":0.999866057},
{"learn":[451.0175847],"iteration":821,"passed_time":4.592260366,"remaining_time":0.9944310769},
{"learn":[450.9191581],"iteration":822,"passed_time":4.596827832,"remaining_time":0.9886251837},
{"learn":[450.8744245],"iteration":823,"passed_time":4.602762429,"remaining_time":0.9831143052},
{"learn":[450.8097366],"iteration":824,"passed_time":4.607884937,"remaining_time":0.9774301381},
{"learn":[450.7468205],"iteration":825,"passed_time":4.612910161,"remaining_time":0.9717268378},
{"learn":[450.669934],"iteration":826,"passed_time":4.618192585,"remaining_time":0.9660789809},
{"learn":[450.6359323],"iteration":827,"passed_time":4.623566322,"remaining_time":0.9604509751},
{"learn":[450.5328682],"iteration":828,"passed_time":4.62827,"remaining_time":0.9546853679},
{"learn":[450.3617908],"iteration":829,"passed_time":4.633634705,"remaining_time":0.9490577107},
{"learn":[450.2557887],"iteration":830,"passed_time":4.639170108,"remaining_time":0.943465401},
{"learn":[450.23183],"iteration":831,"passed_time":4.644273434,"remaining_time":0.937785982},
{"learn":[450.0870815],"iteration":832,"passed_time":4.649298989,"remaining_time":0.9320923544},
{"learn":[450.0233848],"iteration":833,"passed_time":4.654353945,"remaining_time":0.9264061809},
{"learn":[449.9940098],"iteration":834,"passed_time":4.659513147,"remaining_time":0.9207421189},
{"learn":[449.8950689],"iteration":835,"passed_time":4.663620533,"remaining_time":0.9148729275},
{"learn":[449.8940165],"iteration":836,"passed_time":4.668468324,"remaining_time":0.9091521349},
{"learn":[449.8668408],"iteration":837,"passed_time":4.673742674,"remaining_time":0.9035158869},
{"learn":[449.7378486],"iteration":838,"passed_time":4.6784567,"remaining_time":0.8977729782},
{"learn":[449.7313251],"iteration":839,"passed_time":4.683015129,"remaining_time":0.8920028818},
{"learn":[449.6835314],"iteration":840,"passed_time":4.688122316,"remaining_time":0.8863394153},
{"learn":[449.5431495],"iteration":841,"passed_time":4.69407052,"remaining_time":0.8808350857},
{"learn":[449.4770218],"iteration":842,"passed_time":4.700319209,"remaining_time":0.8753856652},
{"learn":[449.4361732],"iteration":843,"passed_time":4.705092494,"remaining_time":0.8696616458},
{"learn":[449.4125477],"iteration":844,"passed_time":4.709118827,"remaining_time":0.8638028618},
{"learn":[449.3434278],"iteration":845,"passed_time":4.714531108,"remaining_time":0.8582006982},
{"learn":[449.2907442],"iteration":846,"passed_time":4.71973284,"remaining_time":0.8525609498},
{"learn":[449.1432205],"iteration":847,"passed_time":4.724046445,"remaining_time":0.846763042},
{"learn":[449.1277831],"iteration":848,"passed_time":4.728371378,"remaining_time":0.8409706456},
{"learn":[448.966645],"iteration":849,"passed_time":4.735847151,"remaining_time":0.8357377324},
{"learn":[448.9350826],"iteration":850,"passed_time":4.74036977,"remaining_time":0.8299824861},
{"learn":[448.8672221],"iteration":851,"passed_time":4.745596445,"remaining_time":0.824352434},
{"learn":[448.746353],"iteration":852,"passed_time":4.752197489,"remaining_time":0.818960177},
{"learn":[448.7029935],"iteration":853,"passed_time":4.757186524,"remaining_time":0.8132894994},
{"learn":[448.568372],"iteration":854,"passed_time":4.761719858,"remaining_time":0.8075431338},
{"learn":[448.3761105],"iteration":855,"passed_time":4.769790572,"remaining_time":0.8023946757},
{"learn":[448.2592437],"iteration":856,"passed_time":4.773969556,"remaining_time":0.7965900193},
{"learn":[448.2128483],"iteration":857,"passed_time":4.780175597,"remaining_time":0.7911246327},
{"learn":[448.199068],"iteration":858,"passed_time":4.785520076,"remaining_time":0.785516101},
{"learn":[448.1585108],"iteration":859,"passed_time":4.790415419,"remaining_time":0.7798350682},
{"learn":[448.0266672],"iteration":860,"passed_time":4.798391058,"remaining_time":0.7746531441},
{"learn":[447.9492734],"iteration":861,"passed_time":4.805978435,"remaining_time":0.7694025801},
{"learn":[447.8952074],"iteration":862,"passed_time":4.811373328,"remaining_time":0.7637985469},
{"learn":[447.8474597],"iteration":863,"passed_time":4.816675587,"remaining_time":0.7581804165},
{"learn":[447.7882633],"iteration":864,"passed_time":4.821665227,"remaining_time":0.7525142262},
{"learn":[447.7736939],"iteration":865,"passed_time":4.826120738,"remaining_time":0.7467669502},
{"learn":[447.7300497],"iteration":866,"passed_time":4.83154032,"remaining_time":0.7411705451},
{"learn":[447.6616621],"iteration":867,"passed_time":4.836483228,"remaining_time":0.7355020577},
{"learn":[447.610628],"iteration":868,"passed_time":4.841085753,"remaining_time":0.7297839282},
{"learn":[447.5214944],"iteration":869,"passed_time":4.847080091,"remaining_time":0.7242763354},
{"learn":[447.4985403],"iteration":870,"passed_time":4.851236735,"remaining_time":0.7184954521},
{"learn":[447.4244585],"iteration":871,"passed_time":4.855387734,"remaining_time":0.7127174656},
{"learn":[447.4112317],"iteration":872,"passed_time":4.861182606,"remaining_time":0.7071823493},
{"learn":[447.2597838],"iteration":873,"passed_time":4.866174977,"remaining_time":0.7015309463},
{"learn":[447.2198872],"iteration":874,"passed_time":4.87083083,"remaining_time":0.6958329758},
{"learn":[447.1022265],"iteration":875,"passed_time":4.877333623,"remaining_time":0.6903988234},
{"learn":[447.003789],"iteration":876,"passed_time":4.88296615,"remaining_time":0.6848401783},
{"learn":[446.9673349],"iteration":877,"passed_time":4.887351982,"remaining_time":0.6791081342},
{"learn":[446.8796754],"iteration":878,"passed_time":4.893225282,"remaining_time":0.6735839126},
{"learn":[446.8175014],"iteration":879,"passed_time":4.898644821,"remaining_time":0.6679970211},
{"learn":[446.6732933],"iteration":880,"passed_time":4.903927417,"remaining_time":0.6623920121},
{"learn":[446.6146633],"iteration":881,"passed_time":4.909589197,"remaining_time":0.6568384639},
{"learn":[446.498565],"iteration":882,"passed_time":4.915202147,"remaining_time":0.6512782006},
{"learn":[446.4470513],"iteration":883,"passed_time":4.919523381,"remaining_time":0.645548317},
{"learn":[446.3740347],"iteration":884,"passed_time":4.924575698,"remaining_time":0.6399166161},
{"learn":[446.3152518],"iteration":885,"passed_time":4.930725209,"remaining_time":0.634427397},
{"learn":[446.2388189],"iteration":886,"passed_time":4.935545658,"remaining_time":0.6287673724},
{"learn":[446.114614],"iteration":887,"passed_time":4.940395807,"remaining_time":0.6231129847},
{"learn":[446.0677478],"iteration":888,"passed_time":4.946036476,"remaining_time":0.61755911},
{"learn":[445.9889356],"iteration":889,"passed_time":4.950970786,"remaining_time":0.6119177376},
{"learn":[445.8992976],"iteration":890,"passed_time":4.956706481,"remaining_time":0.6063759893},
{"learn":[445.8462484],"iteration":891,"passed_time":4.961875529,"remaining_time":0.6007651986},
{"learn":[445.764482],"iteration":892,"passed_time":4.966085688,"remaining_time":0.5950405024},
{"learn":[445.6784333],"iteration":893,"passed_time":4.973623225,"remaining_time":0.5897137158},
{"learn":[445.6375005],"iteration":894,"passed_time":4.979206937,"remaining_time":0.5841527692},
{"learn":[445.5532023],"iteration":895,"passed_time":4.984018485,"remaining_time":0.5785021455},
{"learn":[445.4722179],"iteration":896,"passed_time":4.990629107,"remaining_time":0.5730599755},
{"learn":[445.4300704],"iteration":897,"passed_time":4.996909243,"remaining_time":0.5675776645},
{"learn":[445.4218399],"iteration":898,"passed_time":5.001701409,"remaining_time":0.5619264097},
{"learn":[445.3617423],"iteration":899,"passed_time":5.00767983,"remaining_time":0.55640887},
{"learn":[445.3230095],"iteration":900,"passed_time":5.012069919,"remaining_time":0.5507157847},
{"learn":[445.2815892],"iteration":901,"passed_time":5.017045934,"remaining_time":0.5450892478},
{"learn":[445.1564191],"iteration":902,"passed_time":5.022499244,"remaining_time":0.5395154226},
{"learn":[445.0739743],"iteration":903,"passed_time":5.027497595,"remaining_time":0.5338935499},
{"learn":[445.010761],"iteration":904,"passed_time":5.032242726,"remaining_time":0.528246474},
{"learn":[444.9388871],"iteration":905,"passed_time":5.037437591,"remaining_time":0.5226480502},
{"learn":[444.8014125],"iteration":906,"passed_time":5.043598488,"remaining_time":0.5171495694},
{"learn":[444.7712435],"iteration":907,"passed_time":5.047760412,"remaining_time":0.5114470902},
{"learn":[444.7018874],"iteration":908,"passed_time":5.052652747,"remaining_time":0.505821122},
{"learn":[444.5970245],"iteration":909,"passed_time":5.058429489,"remaining_time":0.5002842352},
{"learn":[444.5518417],"iteration":910,"passed_time":5.063583666,"remaining_time":0.4946860003},
{"learn":[444.4378734],"iteration":911,"passed_time":5.06921965,"remaining_time":0.4891352294},
{"learn":[444.3815793],"iteration":912,"passed_time":5.074968174,"remaining_time":0.4835949958},
{"learn":[444.3280854],"iteration":913,"passed_time":5.079094514,"remaining_time":0.477901672},
{"learn":[444.2663354],"iteration":914,"passed_time":5.083197691,"remaining_time":0.4722096216},
{"learn":[444.2170873],"iteration":915,"passed_time":5.089813082,"remaining_time":0.466751418},
{"learn":[444.1482403],"iteration":916,"passed_time":5.094144269,"remaining_time":0.4610839415},
{"learn":[444.0967056],"iteration":917,"passed_time":5.098567977,"remaining_time":0.4554276406},
{"learn":[444.0446533],"iteration":918,"passed_time":5.10488181,"remaining_time":0.4499406166},
{"learn":[443.9838958],"iteration":919,"passed_time":5.109775496,"remaining_time":0.444328304},
{"learn":[443.8239479],"iteration":920,"passed_time":5.113837545,"remaining_time":0.4386462172},
{"learn":[443.7731823],"iteration":921,"passed_time":5.11950731,"remaining_time":0.4331036553},
{"learn":[443.6552683],"iteration":922,"passed_time":5.124737014,"remaining_time":0.4275241063},
{"learn":[443.5915554],"iteration":923,"passed_time":5.129490055,"remaining_time":0.4219061084},
{"learn":[443.4993355],"iteration":924,"passed_time":5.134269203,"remaining_time":0.4162920976},
{"learn":[443.4026735],"iteration":925,"passed_time":5.140128412,"remaining_time":0.4107662014},
{"learn":[443.2521913],"iteration":926,"passed_time":5.144563442,"remaining_time":0.405127434},
{"learn":[443.2415559],"iteration":927,"passed_time":5.149747897,"remaining_time":0.3995494058},
{"learn":[443.1871241],"iteration":928,"passed_time":5.157591862,"remaining_time":0.3941754814},
{"learn":[443.1442954],"iteration":929,"passed_time":5.161711327,"remaining_time":0.3885159064},
{"learn":[443.0937232],"iteration":930,"passed_time":5.167231853,"remaining_time":0.3829634778},
{"learn":[443.073606],"iteration":931,"passed_time":5.172358683,"remaining_time":0.3773823932},
{"learn":[442.9907175],"iteration":932,"passed_time":5.177460795,"remaining_time":0.3718005072},
{"learn":[442.8524539],"iteration":933,"passed_time":5.183623932,"remaining_time":0.3662946247},
{"learn":[442.8340906],"iteration":934,"passed_time":5.189314724,"remaining_time":0.3607544995},
{"learn":[442.7727369],"iteration":935,"passed_time":5.193996951,"remaining_time":0.3551450906},
{"learn":[442.6542994],"iteration":936,"passed_time":5.199637091,"remaining_time":0.3496020669},
{"learn":[442.6034799],"iteration":937,"passed_time":5.204317576,"remaining_time":0.3439954048},
{"learn":[442.576365],"iteration":938,"passed_time":5.208968031,"remaining_time":0.3383887646},
{"learn":[442.5430831],"iteration":939,"passed_time":5.212972909,"remaining_time":0.3327429517},
{"learn":[442.4422725],"iteration":940,"passed_time":5.21855615,"remaining_time":0.3271995886},
{"learn":[442.3287116],"iteration":941,"passed_time":5.224057536,"remaining_time":0.3216511009},
{"learn":[442.1979421],"iteration":942,"passed_time":5.229061565,"remaining_time":0.3160726503},
{"learn":[442.1401938],"iteration":943,"passed_time":5.234448114,"remaining_time":0.3105181084},
{"learn":[442.0268593],"iteration":944,"passed_time":5.241071541,"remaining_time":0.3050359098},
{"learn":[441.9808949],"iteration":945,"passed_time":5.246309452,"remaining_time":0.2994722098},
{"learn":[441.8402544],"iteration":946,"passed_time":5.252848096,"remaining_time":0.2939819948},
{"learn":[441.7591772],"iteration":947,"passed_time":5.258495669,"remaining_time":0.2884406907},
{"learn":[441.7192049],"iteration":948,"passed_time":5.263687192,"remaining_time":0.2828746541},
{"learn":[441.6325873],"iteration":949,"passed_time":5.268930875,"remaining_time":0.2773121513},
{"learn":[441.578131],"iteration":950,"passed_time":5.273773715,"remaining_time":0.2717296656},
{"learn":[441.5631961],"iteration":951,"passed_time":5.278827693,"remaining_time":0.2661593795},
{"learn":[441.4737555],"iteration":952,"passed_time":5.283841743,"remaining_time":0.2605882077},
{"learn":[441.4236115],"iteration":953,"passed_time":5.289330865,"remaining_time":0.2550411109},
{"learn":[441.326209],"iteration":954,"passed_time":5.293878358,"remaining_time":0.2494497656},
{"learn":[441.2055299],"iteration":955,"passed_time":5.299449857,"remaining_time":0.243907734},
{"learn":[441.1601325],"iteration":956,"passed_time":5.305626131,"remaining_time":0.2383928147},
{"learn":[441.007621],"iteration":957,"passed_time":5.309772967,"remaining_time":0.2327875413},
{"learn":[440.9695935],"iteration":958,"passed_time":5.315417083,"remaining_time":0.2272493226},
{"learn":[440.8673974],"iteration":959,"passed_time":5.321224987,"remaining_time":0.2217177078},
{"learn":[440.7418416],"iteration":960,"passed_time":5.325737968,"remaining_time":0.2161329664},
{"learn":[440.7133071],"iteration":961,"passed_time":5.331436691,"remaining_time":0.2105972913},
{"learn":[440.6381069],"iteration":962,"passed_time":5.336518439,"remaining_time":0.2050375724},
{"learn":[440.5033524],"iteration":963,"passed_time":5.340795886,"remaining_time":0.199448809},
{"learn":[440.4843542],"iteration":964,"passed_time":5.346841696,"remaining_time":0.1939269009},
{"learn":[440.4395292],"iteration":965,"passed_time":5.35308682,"remaining_time":0.1884109233},
{"learn":[440.4087745],"iteration":966,"passed_time":5.357604813,"remaining_time":0.1828344972},
{"learn":[440.3378781],"iteration":967,"passed_time":5.36314445,"remaining_time":0.1772940314},
{"learn":[440.2461585],"iteration":968,"passed_time":5.368361968,"remaining_time":0.1717432621},
{"learn":[440.1085753],"iteration":969,"passed_time":5.37250675,"remaining_time":0.1661600026},
{"learn":[440.0561479],"iteration":970,"passed_time":5.377688791,"remaining_time":0.1606106848},
{"learn":[439.9758239],"iteration":971,"passed_time":5.382697496,"remaining_time":0.1550571295},
{"learn":[439.9259888],"iteration":972,"passed_time":5.387234522,"remaining_time":0.1494916054},
{"learn":[439.79332],"iteration":973,"passed_time":5.391570311,"remaining_time":0.1439228214},
{"learn":[439.7199584],"iteration":974,"passed_time":5.397104576,"remaining_time":0.1383872968},
{"learn":[439.6685231],"iteration":975,"passed_time":5.401889521,"remaining_time":0.1328333489},
{"learn":[439.6216016],"iteration":976,"passed_time":5.406105185,"remaining_time":0.1272675735},
{"learn":[439.6025404],"iteration":977,"passed_time":5.412608765,"remaining_time":0.1217560254},
{"learn":[439.4956767],"iteration":978,"passed_time":5.417651698,"remaining_time":0.1162111192},
{"learn":[439.4040363],"iteration":979,"passed_time":5.422301965,"remaining_time":0.1106592238},
{"learn":[439.3072447],"iteration":980,"passed_time":5.428755505,"remaining_time":0.1051440924},
{"learn":[439.1852715],"iteration":981,"passed_time":5.433759051,"remaining_time":0.0996004714},
{"learn":[439.0745416],"iteration":982,"passed_time":5.437997727,"remaining_time":0.09404472163},
{"learn":[438.9900976],"iteration":983,"passed_time":5.444302155,"remaining_time":0.08852523829},
{"learn":[438.8650183],"iteration":984,"passed_time":5.44864551,"remaining_time":0.0829742971},
{"learn":[438.8120231],"iteration":985,"passed_time":5.454857579,"remaining_time":0.07745233885},
{"learn":[438.7536754],"iteration":986,"passed_time":5.460605127,"remaining_time":0.07192286389},
{"learn":[438.5765721],"iteration":987,"passed_time":5.465721842,"remaining_time":0.06638528553},
{"learn":[438.5077698],"iteration":988,"passed_time":5.470463716,"remaining_time":0.06084438916},
{"learn":[438.4379312],"iteration":989,"passed_time":5.477168059,"remaining_time":0.05532492988},
{"learn":[438.4199783],"iteration":990,"passed_time":5.481478046,"remaining_time":0.04978133442},
{"learn":[438.3216446],"iteration":991,"passed_time":5.486151374,"remaining_time":0.04424315624},
{"learn":[438.3036982],"iteration":992,"passed_time":5.491872912,"remaining_time":0.03871410915},
{"learn":[438.2656765],"iteration":993,"passed_time":5.496772099,"remaining_time":0.03317971086},
{"learn":[438.2339796],"iteration":994,"passed_time":5.501132233,"remaining_time":0.02764388057},
{"learn":[438.2147527],"iteration":995,"passed_time":5.506670387,"remaining_time":0.02211514212},
{"learn":[438.1783479],"iteration":996,"passed_time":5.511153889,"remaining_time":0.0165832113},
{"learn":[438.1251375],"iteration":997,"passed_time":5.516529765,"remaining_time":0.01105516987},
{"learn":[437.9223509],"iteration":998,"passed_time":5.52160073,"remaining_time":0.005527127858},
{"learn":[437.7930372],"iteration":999,"passed_time":5.52714062,"remaining_time":0}
]}